Workbook
Name \0: #N/A
Name \a: #N/A
Name LABEL_AIRE: '[1]MASTER Finishing Price List'!#REF!
Name NONAUXS_4: #REF!
Name Print_Area_MI: #REF!
Name TABLE: '[2]Piece Weight Calculation'!#REF!

Sheet SCOPE
B1: Scope of Tool
B3: For Estimator's use
B4: Perfect Bound and Saddle Stitched products
B5: Comparison tool to your estimating tool

Sheet USA & Canada
A1: L'Occitane, Inc.
A2: Regular Mailers
A3: 44950
A4: Revised 1/26/23
A5: Revised 2/13/23
A7: 2023 RFP
A8: Mailer Name | B8: MTH | C8: Country | D8: Contact Type | E8: OE | F8: Insert | G8: Size | H8: Ink | I8: Personalization | J8: Finishing / Mailing | K8: Data | L8: Cover /Text Paper | M8: Local Box | N8: Paper release / LDC | O8: Mail Vol | P8: IN HOME (MAILINGS) | Q8: Total Pricing | R8: Additional Ms | S8: Assumptions | T8: Pc Wt (#s) | U8: Non-Commingle Postage | V8: Commingle Postage
A9: MOTHER'S DAY | B9: APRIL | C9: USA | D9: 6p+4p Stitched Booklet Mailer | E9: NA | F9: NA | G9: 5.5 x 7.25 Finished | H9: 4cp/4cp | I9: Black address only + store location on mailing panel (4" area maximum) | J9: Stitch, tab (3), tray mail letter rate | K9: Presort Bundle (assumes one file in and out) | L9: 80# matte cover | O9: 500000 | P9: 44666 | Q9: 117479.68 | R9: 226.59294 | S9: Pricing assumes: 1 version included and common art files provided for both USA & Canada. PDF proofs and production ready files provided by client. Hard copy color proofs are $30/each. All data including store location provided in a single file per event. Canadian data and postage pricing assumes client is providing a presorted file. Please note all materials including paper are subject to market pricing and availability. | T9: 0.603 | U9: 0.328 | V9: 0.316
A10: MOTHER'S DAY | B10: APRIL | C10: CANADA | D10: 6p+4p Stitched Booklet Mailer | E10: NA | F10: NA | G10: 5.5 x 7.25 Finished | H10: 4cp/4cp | I10: Black address only + store location on mailing panel (4" area maximum) | J10: Stitch, tab (3), tray mail letter rate | K10: Presort Bundle (assumes one file in and out) | L10: 80# matte cover | O10: 90000 | P10: 44666 | Q10: 21146.343 | R10: 226.59294 | T10: 0.0603 | U10: 0.53193333 | V10: NA
A11: STAR ALMOND | B11: MAY | C11: USA | D11: Folded Self Mailer | E11: NA | F11: NA | G11: Bifold 7x10.5 flat 7x5.25 finished | H11: 4cp/4cp | I11: Black address only + store location on mailing panel (4" area maximum) | J11: Score, fold, tack glue, tray mail letter rate | K11: Presort Bundle (assumes one file in and out) | L11: 100# uncoated cvr | O11: 200000 | P11: 44690 | Q11: 23865.459 | R11: 109.95782 | S11: Pricing assumes: 1 version included and common art files provided for both USA & Canada. PDF proofs and production ready files provided by client. Hard copy color proofs are $30/each. All data including store location provided in a single file per event. Canadian data and postage pricing assumes client is providing a presorted file. Please note all materials including paper are subject to market pricing and availability. | T11: 0.0292 | U11: 0.32598 | V11: 0.316
A12: STAR ALMOND | B12: MAY | C12: CANADA | D12: Folded Self Mailer | E12: NA | F12: NA | G12: Bifold 7x10.5 flat 7x5.25 finished | H12: 4cp/4cp | I12: Black address only + store location on mailing panel (4" area maximum) | J12: Score, fold, tack glue, tray mail letter rate | K12: Presort Bundle (assumes one file in and out) | L12: 100# uncoated cvr | O12: 85000 | P12: 44690 | Q12: 10142.82 | R12: 109.95782 | T12: 0.0292 | U12: 0.53064706 | V12: NA
A13: SUMMER SALE POSTCARD | B13: JUNE | C13: USA | D13: Folded Self Mailer | E13: NA | F13: NA | G13: Trifold 7 x 15.625 flat 7x5.25 finished | H13: 4cp/4cp | I13: Black address only + store location on mailing panel (4" area maximum) | J13: Score, fold, tack glue, tray mail letter rate | K13: Presort Bundle (assumes one file in and out) | L13: 100# uncoated cvr | O13: 250000 | P13: 44718 | Q13: 40273.216 | R13: 152.33958 | S13: Pricing assumes: 1 version included and common art files provided for both USA & Canada. PDF proofs and production ready files provided by client. Hard copy color proofs are $30/each. All data including store location provided in a single file per event. Canadian data and postage pricing assumes client is providing a presorted file. Please note all materials including paper are subject to market pricing and availability. | T13: 0.0434 | U13: 0.327728 | V13: 0.315
A14: SUMMER SALE POSTCARD | B14: JUNE | C14: CANADA | D14: Folded Self Mailer | E14: NA | F14: NA | G14: Trifold 7 x 15.625 flat 7x5.25 finished | H14: 4cp/4cp | I14: Black address only + store location on mailing panel (4" area maximum) | J14: Score, fold, tack glue, tray mail letter rate | K14: Presort Bundle (assumes one file in and out) | L14: 100# uncoated cvr | O14: 50000 | P14: 44718 | Q14: 8054.6433 | R14: 152.33958 | T14: 0.0434 | U14: 0.5346 | V14: NA
A15: STAR INGREDIENTS verbena classic/mint | B15: JULY | C15: USA | D15: Postcard | E15: NA | F15: NA | G15: 8 x 6 | H15: 4cp/4cp | I15: Black address only + store location on mailing panel (4" area maximum) | J15: Trim, tack glue, tray mail letter rate | K15: Presort Bundle (assumes one file in and out) | L15: 100# uncoated cvr | O15: 200000 | P15: 44734 | Q15: 14502.247 | R15: 65.280653 | S15: Pricing assumes: 1 version included and common art files provided for both USA & Canada. PDF proofs and production ready files provided by client. Hard copy color proofs are $30/each. All data including store location provided in a single file per event. Canadian data and postage pricing assumes client is providing a presorted file. Please note all materials including paper are subject to market pricing and availability. | T15: 0.019 | U15: 0.32397 | V15: 0.316
A16: STAR INGREDIENTS verbena classic/mint | B16: JULY | C16: CANADA | D16: Postcard | E16: NA | F16: NA | G16: 8 x 6 | H16: 4cp/4cp | I16: Black address only + store location on mailing panel (4" area maximum) | J16: Trim, tack glue, tray mail letter rate | K16: Presort Bundle (assumes one file in and out) | L16: 100# uncoated cvr | O16: 70000 | P16: 44734 | Q16: 5075.7863 | R16: 65.280653 | T16: 0.019 | U16: 0.53185714 | V16: NA
A17: DIVINE SKINCARE/BEST SELLERS | B17: AUGUST | C17: USA | D17: Folded Self Mailer | E17: NA | F17: NA | G17: Trifold 7 x 15.625 flat 7x5.25 finished | H17: 4cp/4cp | I17: Black address only + store location on mailing panel (4" area maximum) | J17: Score, fold, tack glue, tray mail letter rate | K17: Presort Bundle (assumes one file in and out) | L17: 100# uncoated cvr | O17: 250000 | P17: 44769 | Q17: 40273.216 | R17: 152.33958 | S17: Pricing assumes: 1 version included and common art files provided for both USA & Canada. PDF proofs and production ready files provided by client. Hard copy color proofs are $30/each. All variable data includes store location provided in a single file per event. Canadian data and postage pricing assumes client is providing a presorted file. Please note all materials including paper are subject to market pricing and availability. | T17: 0.0434 | U17: 0.327728 | V17: 0.315
A18: DIVINE SKINCARE/BEST SELLERS | B18: AUGUST | C18: CANADA | D18: Folded Self Mailer | E18: NA | F18: NA | G18: Trifold 7 x 15.625 flat 7x5.25 finished | H18: 4cp/4cp | I18: Black address only + store location on mailing panel (4" area maximum) | J18: Score, fold, tack glue, tray mail letter rate | K18: Presort Bundle (assumes one file in and out) | L18: 100# uncoated cvr | O18: 50000 | P18: 44769 | Q18: 8054.6433 | R18: 152.33958 | T18: 0.0434 | U18: 0.5346
A19: PRECIOUS RELAUNCH | B19: SEPTEMBER | C19: USA | D19: Folded Self Mailer | E19: NA | F19: NA | G19: Trifold 7 x 15.625 flat 7x5.25 finished | H19: 4cp/4cp | I19: Black address only + store location on mailing panel (4" area maximum) | J19: Score, fold, tack glue, tray mail letter rate | K19: Presort Bundle (assumes one file in and out) | L19: 100# uncoated cvr | O19: 340000 | P19: 44804 | Q19: 53878.324 | R19: 152.35872 | S19: Pricing assumes: 1 version included and common art files provided for both USA & Canada. PDF proofs and production ready files provided by client. Hard copy color proofs are $30/each. All data includes store location provided in a single file per event. Please note all materials including paper are subject to market pricing and availability. | T19: 0.0434 | U19: 0.32669706 | V19: 0.315
A20: PRECIOUS RELAUNCH | B20: SEPTEMBER | C20: CANADA | D20: Folded Self Mailer | E20: NA | F20: NA | G20: Trifold 7 x 15.625 flat 7x5.25 finished | H20: 4cp/4cp | I20: Black address only + store location on mailing panel (4" area maximum) | J20: Score, fold, tack glue, tray mail letter rate | K20: Presort Bundle (assumes one file in and out) | L20: 100# uncoated cvr | O20: 90000 | P20: 44804 | Q20: 14261.909 | R20: 152.35872 | T20: 0.0434 | U20: 0.53033333 | V20: NA
A21: CUSTOMER APPRECIATION | B21: SEPTEMBER | C21: USA | D21: Postcard | E21: NA | F21: NA | G21: 8 x 6 | H21: 4cp/4cp | I21: Black address only + store location on mailing panel (4" area maximum) | J21: Trim, tack glue, tray mail letter rate | K21: Presort Bundle (assumes one file in and out) | L21: 100# Anthem Matte cover FSC | O21: 600000 | P21: 44818 | Q21: 38817.466 | R21: 62.255456 | S21: Pricing assumes: 1 version included and common art files provided for both USA & Canada. PDF proofs and production ready files provided by client. Hard copy color proofs are $30/each. All data includes store location provided in a single file per event. Please note all materials including paper are subject to market pricing and availability. | T21: 0.019 | U21: 0.31754833 | V21: 0.312
A22: CUSTOMER APPRECIATION | B22: SEPTEMBER | C22: CANADA | D22: Postcard | E22: NA | F22: NA | G22: 8 x 6 | H22: 4cp/4cp | I22: Black address only + store location on mailing panel (4" area maximum) | J22: Trim, tack glue, tray mail letter rate | K22: Presort Bundle (assumes one file in and out) | L22: 100# Anthem Matte cover FSC | O22: 200000 | P22: 44818 | Q22: 12939.155 | R22: 62.255456 | T22: 0.019 | U22: 0.5274 | V22: NA
A23: PRE-HOLIDAY | B23: OCTOBER | C23: USA | D23: Folded Self Mailer | E23: NA | F23: NA | G23: Trifold 7 x 15.625 flat 7x5.25 finished | H23: 4cp/4cp | I23: Black address only + store location on mailing panel (4" area maximum) | J23: Score, fold, tack glue, tray mail letter rate | K23: Presort Bundle (assumes one file in and out) | L23: 100# uncoated cvr | O23: 400000 | P23: 44839 | Q23: 62998.614 | R23: 62.255456 | S23: Pricing assumes: 1 version included and common art files provided for both USA & Canada. PDF proofs and production ready files provided by client. Hard copy color proofs are $30/each. All data including store location provided in a single file per event. Canadian data and postage pricing assumes client is providing a presorted file. Please note all materials including paper are subject to market pricing and availability. | T23: 0.0434 | U23: 0.3265525 | V23: 0.315
A24: PRE-HOLIDAY | B24: OCTOBER | C24: CANADA | D24: Folded Self Mailer | E24: NA | F24: NA | G24: Trifold 7 x 15.625 flat 7x5.25 finished | H24: 4cp/4cp | I24: Black address only + store location on mailing panel (4" area maximum) | J24: Score, fold, tack glue, tray mail letter rate | K24: Presort Bundle (assumes one file in and out) | L24: 100# uncoated cvr | O24: 110000 | P24: 44839 | Q24: 17324.619 | R24: 62.255456 | T24: 0.0434 | U24: 0.52992727 | V24: NA
A25: HOLIDAY 1 CATALOG | B25: NOVEMBER | C25: USA | D25: Envelope Package with Catalog (20 Pg + 4pg) + 2pg Insert | E25: 6x9 Booklet OE (flap on long side*), closed faced, 4CP outside, heavy coverage, bleeds, knock out for address on flap seal side, 7pt uncoated (100# opaque text)** | F25: 2pg 5.5 x 7.25, 4/4, with scent seal | G25: 5.5 x 7.25 Finished | H25: 4cp/4cp | I25: Black address only + store location on mailing panel (4" area maximum) | J25: Stitch book,apply scent seal to 2pg card (customer-supplied) Insert 2 into OE, image black address only, no match, tray mail flat | K25: Presort Bundle (assumes one file in and out) | L25: Mohawk Uncoated Via Smooth 80# Cover | O25: 250000 | P25: 44868 | Q25: 222771.68 | R25: 873.72214 | S25: Pricing assumes: 1 version included and common art files provided for both USA & Canada. PDF proofs and production ready files provided by client. Hard copy color proofs are $30/each. Scent Seal provided to Quad as an labelaire on a roll All data includes store location provided in a single file per event. Canadian data and postage pricing assumes client is providing a presorted file. Please note all materials including paper are subject to market pricing and availability. | T25: 0.2053 | U25: 0.360488 | V25: 0.331
A26: HOLIDAY 1 CATALOG | B26: NOVEMBER | C26: CANADA | D26: Envelope Package with Catalog (20 Pg + 4pg) + 2pg Insert | E26: 6x9 Booklet OE (flap on long side*), closed faced, 4CP outside, heavy coverage, bleeds, knock out for address on flap seal side, 7pt uncoated (100# opaque text)** | F26: 2pg 5.5 x 7.25, 4/4, with scent seal | G26: 5.5 x 7.25 Finished | H26: 4cp/4cp | I26: Black address only + store location on mailing panel (4" area maximum) | J26: Stitch book,apply scent seal to 2pg card (customer-supplied) Insert 2 into OE, image black address only, no match, tray mail flat | K26: Presort Bundle (assumes one file in and out) | L26: Mohawk Uncoated Via Smooth 80# Cover | O26: 50000 | P26: 44868 | Q26: 44554.337 | R26: 873.72214 | S26: Pricing assumes: 1 version included and common art files provided for both USA & Canada. PDF proofs and production ready files provided by client. Hard copy color proofs are $30/each. Scent Seal provided to Quad as an labelaire on a roll All data includes store location provided in a single file per event. Canadian data and postage pricing assumes client is providing a presorted file. Please note all materials including paper are subject to market pricing and availability. | T26: 0.2053 | U26: 0.96442 | V26: NA
A27: HOLIDAY 1 CATALOG | B27: NOVEMBER | C27: USA & CANADA | D27: Scented Label RCR Clear BOPP/Clear BOPP Permanent Label Encapsulated Fragrance Snap & Burst | E27: NA | F27: NA | G27: 2x2 Finished | H27: Clear | I27: none | J27: NA | K27: NA | L27: Stock #249 2 Clear BOPP W/Operm Adhesive/ Stock #249 2 Clear BOPP W/Operm Adhesive | O27: 300000 | P27: 44868 | Q27: 18415.755 | R27: 61.38585 | S27: Pricing assumes: Fragrence oil is supplied by the client to vendor for encapsulation. Schedule TBD depending on delivery of oil. Pricing valid for 30 days. Please note all materials are subject to market pricing and availability.
A28: BF/CM POSTCARD | B28: NOVEMBER | C28: USA | D28: Postcard | E28: NA | F28: NA | G28: 8 x 6 | H28: 4cp/4cp | I28: Black address only + store location on mailing panel (4" area maximum) | J28: Trim, tack glue, tray mail letter rate | K28: Presort Bundle (assumes one file in and out) | L28: 100# Anthem Matte cover FSC | O28: 1000000 | P28: 44888 | Q28: 60807.572 | R28: 59.210155 | S28: Pricing assumes: 1 version included and common art files provided for both USA & Canada. PDF proofs and production ready files provided by client. Hard copy color proofs are $30/each. All data including store location provided in a single file per event. Canadian data and postage pricing assumes client is providing a presorted file. Please note all materials including paper are subject to market pricing and availability. | T28: 0.019 | U28: 0.307575 | V28: 0.312
A29: BF/CM POSTCARD | B29: NOVEMBER | C29: CANADA | D29: Postcard | E29: NA | F29: NA | G29: 8 x 6 | H29: 4cp/4cp | I29: Black address only + store location on mailing panel (4" area maximum) | J29: Trim, tack glue, tray mail letter rate | K29: Presort Bundle (assumes one file in and out) | L29: 100# Anthem Matte cover FSC | O29: 200000 | P29: 44888 | Q29: 12161.514 | R29: 59.210155 | T29: 0.019 | U29: 0.5274 | V29: NA
A30: HOLIDAY 2 | B30: DECEMBER | C30: USA | D30: Folded Self Mailer | E30: NA | F30: NA | G30: Trifold 7 x 15.625 flat 7x5.25 finished | H30: 4cp/4cp | I30: Black address only + store location on mailing panel (4" area maximum) | J30: Score, fold, tack glue, tray mail letter rate | K30: Presort Bundle (assumes one file in and out) | L30: 100# uncoated cvr | O30: 200000 | P30: 44897 | Q30: 32285.24 | R30: 152.33958 | S30: Pricing assumes: 1 version included and common art files provided for both USA & Canada. PDF proofs and production ready files provided by client. Hard copy color proofs are $30/each. All data including store location provided in a single file per event. Canadian data and postage pricing assumes client is providing a presorted file. Please note all materials including paper are subject to market pricing and availability. | T30: 0.0434 | U30: 0.328775 | V30: 0.318
A31: HOLIDAY 2 | B31: DECEMBER | C31: CANADA | D31: Folded Self Mailer | E31: NA | F31: NA | G31: Trifold 7 x 15.625 flat 7x5.25 finished | H31: 4cp/4cp | I31: Black address only + store location on mailing panel (4" area maximum) | J31: Score, fold, tack glue, tray mail letter rate | K31: Presort Bundle (assumes one file in and out) | L31: 100# uncoated cvr | O31: 100000 | P31: 44897 | Q31: 16142.62 | R31: 152.33958 | T31: 0.0434 | U31: 0.53002 | V31: NA
A32: WINTER SALE | B32: JANUARY | C32: USA | D32: Postcard | E32: NA | F32: NA | G32: 8 x 6 | H32: 4cp/4cp | I32: Black address only + store location on mailing panel (4" area maximum) | J32: Trim, tack glue, tray mail letter rate | K32: Presort Bundle (assumes one file in and out) | L32: 100# uncoated cvr | O32: 120000 | P32: 44921 | Q32: 8814.0072 | R32: 61.966198 | S32: Pricing assumes: 1 version included and common art files provided for both USA & Canada. PDF proofs and production ready files provided by client. Hard copy color proofs are $30/each. All data including store location provided in a single file per event. Please note all materials including paper are subject to market pricing and availability. | T32: 0.019 | U32: 0.32649167 | V32: 0.316
A33: WINTER SALE | B33: JANUARY | C33: CANADA | D33: Postcard | E33: NA | F33: NA | G33: 8 x 6 | H33: 4cp/4cp | I33: Black address only + store location on mailing panel (4" area maximum) | J33: Trim, tack glue, tray mail letter rate | K33: Presort Bundle (assumes one file in and out) | L33: 100# uncoated cvr | O33: 50000 | P33: 44921 | Q33: 3672.503 | R33: 61.966198 | T33: 0.019 | U33: 0.5346 | V33: NA
A34: SHEA IMMORTELLE ANTI-AGING | B34: FEBRUARY | C34: USA | D34: Folded Self Mailer | E34: NA | F34: NA | G34: Bifold w/ 3" Flap 8 x 15 flat 8x6 finished | H34: 4cp/4cp | I34: Black address only + store location on mailing panel (4" area maximum) | J34: Score, fold, tack glue, tray mail letter rate | K34: Presort Bundle (assumes one file in and out) | L34: 100# uncoated cvr | O34: 190000 | P34: 44937 | Q34: 23222.797 | R34: 109.95782 | S34: Pricing assumes: 1 version included and common art files provided for both USA & Canada. PDF proofs and production ready files provided by client. Hard copy color proofs are $30/each. All data including store location provided in a single file per event. Canadian data and postage pricing assumes client is providing a presorted file. Please note all materials including paper are subject to market pricing and availability. | T34: 0.0476 | U34: 0.32976316 | V34: 0.318
A35: SHEA IMMORTELLE ANTI-AGING | B35: FEBRUARY | C35: CANADA | D35: Folded Self Mailer | E35: NA | F35: NA | G35: Bifold w/ 3" Flap 8 x 15 flat 8x6 finished | H35: 4cp/4cp | I35: Black address only + store location on mailing panel (4" area maximum) | J35: Score, fold, tack glue, tray mail letter rate | K35: Presort Bundle (assumes one file in and out) | L35: 100# uncoated cvr | O35: 85000 | P35: 44937 | Q35: 10389.146 | R35: 109.95782 | T35: 0.0476 | U35: 0.53064706 | V35: NA
A36: FACECARE - best lab in the world is nature | B36: FEBRUARY | C36: USA | D36: Folded Self Mailer | E36: NA | F36: NA | G36: Trifold 7 x 15.625 flat 7x5.25 finished | H36: 4cp/4cp | I36: Black address only + store location on mailing panel (4" area maximum) | J36: Score, fold, tack glue, tray mail letter rate | K36: Presort Bundle (assumes one file in and out) | L36: 100# uncoated cvr | O36: 280000 | P36: 44972 | Q36: 44869.138 | R36: 152.28939 | S36: Pricing assumes: 1 version included and common art files provided for both USA & Canada. PDF proofs and production ready files provided by client. Hard copy color proofs are $30/each. All variable data including store location provided in a single file per event. Canadian data and postage pricing assumes client is providing a presorted file. Please note all materials including paper are subject to market pricing and availability. | T36: 0.0434 | U36: 0.32673571 | V36: 0.315
A37: FACECARE - best lab in the world is nature | B37: FEBRUARY | C37: CANADA | D37: Folded Self Mailer | E37: NA | F37: NA | G37: Trifold 7 x 15.625 flat 7x5.25 finished | H37: 4cp/4cp | I37: Black address only + store location on mailing panel (4" area maximum) | J37: Score, fold, tack glue, tray mail letter rate | K37: Presort Bundle (assumes one file in and out) | L37: 100# uncoated cvr | O37: 50000 | P37: 44972 | Q37: 8012.3461 | R37: 152.28939 | T37: 0.0434 | U37: 0.5346 | V37: NA
A38: FRIENDS & FAMILY | B38: MARCH | C38: USA | D38: Postcard | E38: NA | F38: NA | G38: 8 x 6 | H38: 4cp/4cp | I38: Black address only + store location on mailing panel (4" area maximum) | J38: Trim, tack glue, tray mail letter rate | K38: Presort Bundle (assumes one file in and out) | L38: 100# Anthem Matte cover FSC | O38: 545000 | P38: 45014 | Q38: 33524.825 | R38: 58.892962 | S38: Pricing assumes: 1 version included and common art files provided for both USA & Canada. PDF proofs and production ready files provided by client. Hard copy color proofs are $30/each. All variable data including store location provided in a single file per event. Canadian data and postage pricing assumes client is providing a presorted file. Please note all materials including paper are subject to market pricing and availability. | T38: 0.019 | U38: 0.87176 | V38: 0.312
A39: FRIENDS & FAMILY | B39: MARCH | C39: CANADA | D39: Postcard | E39: NA | F39: NA | G39: 8 x 6 | H39: 4cp/4cp | I39: Black address only + store location on mailing panel (4" area maximum) | J39: Trim, tack glue, tray mail letter rate | K39: Presort Bundle (assumes one file in and out) | L39: 100# Anthem Matte cover FSC | O39: 200000 | P39: =P38 -> 45014 | Q39: 12302.688 | R39: 58.892962 | T39: 0.019 | U39: 0.5274 | V39: NA
O40: =SUM(O9:O39) -> 7105000
E41: *Please Note - flap must be on the long side for machine inserting
A42: US 2021/2022 Holidays | E42: **Envelope quoted on 100# opaque text (7pt) due to machine requirements.
A43: 44199 | C43: New Year’s Day
A44: 44578 | C44: MLK
A45: 44613 | C45: President's Day
A46: 44711 | C46: Memorial Day
A47: 44732 | C47: Juneteenth (6/19)
A48: 44746 | C48: 4th of July (7/4)
A49: 44809 | C49: Labor Day
A50: 44844 | C50: Columbus Day
A51: 44889 | C51: Thanksgiving Day
A52: 44921 | C52: Christmas Day (USA)
A53: 44928 | C53: New Year’s Day
A54: 1000000 | C54: Weekend = Mon
L56: =SUMIF(C9:O39,O56,O9:O39) -> 5325000 | O56: USA
L57: =SUMIF(C10:O40,O57,O10:O40) -> 1480000 | O57: CANADA
L58: =SUM(L56:L57) -> 6805000
L59: =L58-O40 -> -300000
A60: This quotation is based on the specifications supplied at the time of the estimate. Prices are subject to equipment availability and mutual agreement of production schedules. The prices for materials (such as ink, coatings and poly), freight or outside services included in this Agreement/Proposal are based on current pricing and subject to adjustment based on Quad announced market price changes. Unless specifically noted, the pricing in this quote does not reflect any discounts, rebates or sales incentives. Printer reserves the right to review coverage upon receipt of files.
A61: CPM pricing can be run up from or between quantities as needed. CPM pricing is valid for quantities 5% less than the lowest quantity quoted.
A62: Industry standard tolerance of +/‑ 1/16 of an inch may apply to print‑to‑fold and/or fold‑to‑cut operations. Cracking on folds may occur on basis weights over 60 lb. coated text. Matte/Dull/Satin stocks are prone to scuffing. Varnish will mitigate, but not necessarily prevent this occurrence.
A63: The freight estimates are based on the information provided. The actual freight charges will be calculated based on the actual shipment characteristics, current fuel surcharge (subject to change), and any accessorial charges that may be applicable at time of pickup or delivery. The freight estimates assume adequate transit time to ship via the most economical way.
A64: The postage estimate is based on historical data and may not reflect your actual distribution. We strongly encourage supplying data files for further analysis. Estimated total cost to mail includes postage, freight to U.S.P.S. and fee.
A65: The postage estimate is based on historical data and may not reflect your actual distribution. We strongly encourage supplying data files for further analysis. Estimated total cost to mail includes postage, freight to U.S.P.S. and fee.
A66: Title and risk of loss to the finished and semi-finished work will pass to you upon the earlier of: (1) our delivery to a carrier or the Postal Service F.O.B. our shipping dock or (2) our delivery into storage. This is true even if we own the carrier or the storage facility.
A67: Freight and postage are billed separately. You are responsible for all postage. all postage must be deposited with the U.S.P.S. prior to the scheduled mail date. Pool shipping postal savings are not included and will be quoted separately.
A68: Mail date changes for participation in pool shipping cycles must happen prior to the cycle close date. Changes made after this date may be subject to freight costs for mail routed in the specific cycle.
A69: (You are responsible for all postage. Postage is due in accordance with the following unless otherwise stated:
A70: (i) If your finished letter rate pieces are pre-sorted together with one or more other customers in a single mail stream, then you will be quoted a co-mingling rate. We will invoice you for the co-mingling rate that is based upon your requested quantities and estimated piece weight and will include postage, freight, fuel surcharge and processing fees; these charges must be paid to us prior to the start of the co-mingling processing.
A71: (ii) If the postage for our project is stamped or metered, then you will be invoiced for the cost of stamps or metering and such charges must be paid to us prior to the start of stamping or metering.
... A74: In the absence of a master services agreement or similar agreement executed by Quad and Client by which the parties agreed to the terms and conditions applicable to any Work to be performed by Quad, the Work provided for herein is subject to the terms and conditions that are provided and made available to Client on www.Quad.com/clients, including any applicable Addenda. By signing and returning this document (or by placing an order with Quad for the Work), Client agrees to such terms and conditions, including the applicable Addenda, each of which is incorporated herein by reference. Quad reserves the right to revise the terms of this proposal if this Proposal is not accepted within ninety (90) days.

Sheet Price Schedule (2)
A1: TRANSACTIONAL PRICING | R1: What is the Pricing Level? | S1: Use Out The Door Levels | AI1: MR % | AK1: Run/M % | BA1: Price List Attributes | BB1: MR | BC1: Run
A2: Price Schedule - Confidential | S2: 0.08 | U2: Surcharge | AA2: =IF(ISNUMBER(SEARCH("%",S1)),1,0)*AI2 -> 0 | AC2: =IF(ISNUMBER(SEARCH("%",S1)),1,0)*AK2 -> 0 | AI2: 0.2 | AK2: 0.2 | BA2: Use Benchmark Levels | BB2: 11 | BC2: 13
A3: DMC Space | S3: *all rates have been increased by the 8% surcharge | BA3: Use Out The Door Levels | BB3: 15 | BC3: 17
A4: 50# - 12pt | AI4: DO NOT CHANGE | BA4: Use Floor Levels | BB4: 19 | BC4: 21
BA5: % Adjusted From Benchmark | BB5: 27 | BC5: 29
AI6: PROPOSED | AM6: % FROM BENCHMARK | BA6: % Adjusted From Out The Door | BB6: 32 | BC6: 34
K7: BENCHMARK | O7: OUT THE DOOR | S7: FLOOR | W7: MANUAL OVERRIDE | AA7: BM w/ % Change | AE7: OTD w/ % Change | BA7: *** Already tied to $-List - just add to LIST in T1
A9: IMAGING FORMAT | E9: per pg (y or n) | K9: EACH | O9: =K9 -> EACH | Q9: =M9 | S9: =K9 -> EACH | U9: =M9 | W9: =K9 -> EACH | Y9: =M9 | AA9: =K9 -> EACH | AC9: =M9 | AE9: =O9 -> EACH | AG9: =M9 | AI9: =K9 -> EACH | AK9: =M9 | AM9: =K9 -> EACH | AO9: =M9
A10: COMMERCIAL
A11: PDFX1A-DOWNLOAD, POST, PLATE per page | E11: y | K11: 10 | M11: 0 | O11: 8 | Q11: 0 | S11: 4.75 | U11: 0 | AA11: =$K11*(1+$AI$2) -> 12 | AC11: =$M11*(1+$AK$2) -> 0 | AE11: =$O11*(1+$AI$2) -> 9.6 | AG11: =$Q11*(1+$AK$2) -> 0 | AI11: =IF(ISBLANK(W11),VLOOKUP(A11,A11:AG11,VLOOKUP($S$1,'Price Schedule (2)'!$BA$2:$BC$6,2,FALSE),FALSE),W11) -> 8 | AK11: =IF(ISBLANK(Y11),VLOOKUP(A11,A11:AG11,VLOOKUP($S$1,'Price Schedule (2)'!$BA$2:$BC$6,3,FALSE),FALSE),Y11) -> 0 | AM11: =IF(AND(K11=0,W11=0),0,IF(K11=0,"BM is $0",(AI11-K11)/K11)) -> -0.2 | AO11: =IF(AND(M11=0,Y11=0),0,IF(M11=0,"BM is $0",(AK11-M11)/M11)) -> 0
A12: DIGITAL BLUE LINES per page | E12: y | K12: 1.5 | M12: 0 | O12: 1 | Q12: 0 | S12: 0.5 | U12: 0 | AA12: =$K12*(1+$AI$2) -> 1.8 | AC12: =$M12*(1+$AK$2) -> 0 | AE12: =$O12*(1+$AI$2) -> 1.2 | AG12: =$Q12*(1+$AK$2) -> 0 | AI12: =IF(ISBLANK(W12),VLOOKUP(A12,A12:AG12,VLOOKUP($S$1,'Price Schedule (2)'!$BA$2:$BC$6,2,FALSE),FALSE),W12) -> 1 | AK12: =IF(ISBLANK(Y12),VLOOKUP(A12,A12:AG12,VLOOKUP($S$1,'Price Schedule (2)'!$BA$2:$BC$6,3,FALSE),FALSE),Y12) -> 0 | AM12: =IF(AND(K12=0,W12=0),0,IF(K12=0,"BM is $0",(AI12-K12)/K12)) -> -0.33333333 | AO12: =IF(AND(M12=0,Y12=0),0,IF(M12=0,"BM is $0",(AK12-M12)/M12)) -> 0
A13: CONTRACT PROOFS per page | E13: y | K13: 15 | M13: 0 | O13: 15 | Q13: 0 | S13: 6.25 | U13: 0 | AA13: =$K13*(1+$AI$2) -> 18 | AC13: =$M13*(1+$AK$2) -> 0 | AE13: =$O13*(1+$AI$2) -> 18 | AG13: =$Q13*(1+$AK$2) -> 0 | AI13: =IF(ISBLANK(W13),VLOOKUP(A13,A13:AG13,VLOOKUP($S$1,'Price Schedule (2)'!$BA$2:$BC$6,2,FALSE),FALSE),W13) -> 15 | AK13: =IF(ISBLANK(Y13),VLOOKUP(A13,A13:AG13,VLOOKUP($S$1,'Price Schedule (2)'!$BA$2:$BC$6,3,FALSE),FALSE),Y13) -> 0 | AM13: =IF(AND(K13=0,W13=0),0,IF(K13=0,"BM is $0",(AI13-K13)/K13)) -> 0 | AO13: =IF(AND(M13=0,Y13=0),0,IF(M13=0,"BM is $0",(AK13-M13)/M13)) -> 0
A14: CONTRACT PROOFS - CVR ONLY per page | E14: y | K14: 15 | M14: 0 | O14: 15 | Q14: 0 | S14: 6.25 | U14: 0 | AA14: =$K14*(1+$AI$2) -> 18 | AC14: =$M14*(1+$AK$2) -> 0 | AE14: =$O14*(1+$AI$2) -> 18 | AG14: =$Q14*(1+$AK$2) -> 0 | AI14: =IF(ISBLANK(W14),VLOOKUP(A14,A14:AG14,VLOOKUP($S$1,'Price Schedule (2)'!$BA$2:$BC$6,2,FALSE),FALSE),W14) -> 15 | AK14: =IF(ISBLANK(Y14),VLOOKUP(A14,A14:AG14,VLOOKUP($S$1,'Price Schedule (2)'!$BA$2:$BC$6,3,FALSE),FALSE),Y14) -> 0 | AM14: =IF(AND(K14=0,W14=0),0,IF(K14=0,"BM is $0",(AI14-K14)/K14)) -> 0 | AO14: =IF(AND(M14=0,Y14=0),0,IF(M14=0,"BM is $0",(AK14-M14)/M14)) -> 0
A15: NON-CONTRACT PROOFS per page | E15: y | K15: 10 | M15: 0 | O15: 10 | Q15: 0 | S15: 5 | U15: 0 | AA15: =$K15*(1+$AI$2) -> 12 | AC15: =$M15*(1+$AK$2) -> 0 | AE15: =$O15*(1+$AI$2) -> 12 | AG15: =$Q15*(1+$AK$2) -> 0 | AI15: =IF(ISBLANK(W15),VLOOKUP(A15,A15:AG15,VLOOKUP($S$1,'Price Schedule (2)'!$BA$2:$BC$6,2,FALSE),FALSE),W15) -> 10 | AK15: =IF(ISBLANK(Y15),VLOOKUP(A15,A15:AG15,VLOOKUP($S$1,'Price Schedule (2)'!$BA$2:$BC$6,3,FALSE),FALSE),Y15) -> 0 | AM15: =IF(AND(K15=0,W15=0),0,IF(K15=0,"BM is $0",(AI15-K15)/K15)) -> 0 | AO15: =IF(AND(M15=0,Y15=0),0,IF(M15=0,"BM is $0",(AK15-M15)/M15)) -> 0
A16: IMPRESS PROOF | E16: n | K16: 80 | M16: 0 | O16: 40 | Q16: 0 | S16: 30 | U16: 0 | AA16: =$K16*(1+$AI$2) -> 96 | AC16: =$M16*(1+$AK$2) -> 0 | AE16: =$O16*(1+$AI$2) -> 48 | AG16: =$Q16*(1+$AK$2) -> 0 | AI16: =IF(ISBLANK(W16),VLOOKUP(A16,A16:AG16,VLOOKUP($S$1,'Price Schedule (2)'!$BA$2:$BC$6,2,FALSE),FALSE),W16) -> 40 | AK16: =IF(ISBLANK(Y16),VLOOKUP(A16,A16:AG16,VLOOKUP($S$1,'Price Schedule (2)'!$BA$2:$BC$6,3,FALSE),FALSE),Y16) -> 0 | AM16: =IF(AND(K16=0,W16=0),0,IF(K16=0,"BM is $0",(AI16-K16)/K16)) -> -0.5 | AO16: =IF(AND(M16=0,Y16=0),0,IF(M16=0,"BM is $0",(AK16-M16)/M16)) -> 0
A17: N/A | E17: n | K17: 0 | M17: 0 | O17: 0 | Q17: 0 | S17: 0 | U17: 0 | AA17: =$K17*(1+$AI$2) -> 0 | AC17: =$M17*(1+$AK$2) -> 0 | AE17: =$O17*(1+$AI$2) -> 0 | AG17: =$Q17*(1+$AK$2) -> 0 | AI17: =IF(ISBLANK(W17),VLOOKUP(A17,A17:AG17,VLOOKUP($S$1,'Price Schedule (2)'!$BA$2:$BC$6,2,FALSE),FALSE),W17) -> 0 | AK17: =IF(ISBLANK(Y17),VLOOKUP(A17,A17:AG17,VLOOKUP($S$1,'Price Schedule (2)'!$BA$2:$BC$6,3,FALSE),FALSE),Y17) -> 0 | AM17: =IF(AND(K17=0,W17=0),0,IF(K17=0,"BM is $0",(AI17-K17)/K17)) -> 0 | AO17: =IF(AND(M17=0,Y17=0),0,IF(M17=0,"BM is $0",(AK17-M17)/M17)) -> 0
A18: DIRECT MAIL
A19: CUSTOMER CONTRACT COLOR PROOFS per page | E19: y | K19: 50 | M19: 0 | O19: 35 | Q19: 0 | S19: 20 | U19: 0
A20: VARIABLE IMAGING template design | E20: n | K20: 350 | M20: 0 | O20: 250 | Q20: 0 | S20: 100 | U20: 0 | AA20: =$K20*(1+$AI$2) -> 420 | AC20: =$M20*(1+$AK$2) -> 0 | AE20: =$O20*(1+$AI$2) -> 300 | AG20: =$Q20*(1+$AK$2) -> 0 | AI20: =IF(ISBLANK(W20),VLOOKUP(A20,A20:AG20,VLOOKUP($S$1,'Price Schedule (2)'!$BA$2:$BC$6,2,FALSE),FALSE),W20) -> 250 | AK20: =IF(ISBLANK(Y20),VLOOKUP(A20,A20:AG20,VLOOKUP($S$1,'Price Schedule (2)'!$BA$2:$BC$6,3,FALSE),FALSE),Y20) -> 0 | AM20: =IF(AND(K20=0,W20=0),0,IF(K20=0,"BM is $0",(AI20-K20)/K20)) -> -0.28571429 | AO20: =IF(AND(M20=0,Y20=0),0,IF(M20=0,"BM is $0",(AK20-M20)/M20)) -> 0
A21: Alteration files to be billed at base price plus 50%. | AA21: =$K21*(1+$AI$2) -> 0 | AC21: =$M21*(1+$AK$2) -> 0 | AE21: =$O21*(1+$AI$2) -> 0 | AG21: =$Q21*(1+$AK$2) -> 0 | AI21: =IF(ISBLANK(W21),VLOOKUP(A21,A21:AG21,VLOOKUP($S$1,'Price Schedule (2)'!$BA$2:$BC$6,2,FALSE),FALSE),W21) -> 0 | AK21: =IF(ISBLANK(Y21),VLOOKUP(A21,A21:AG21,VLOOKUP($S$1,'Price Schedule (2)'!$BA$2:$BC$6,3,FALSE),FALSE),Y21) -> 0 | AM21: =IF(AND(K21=0,W21=0),0,IF(K21=0,"BM is $0",(AI21-K21)/K21)) -> 0 | AO21: =IF(AND(M21=0,Y21=0),0,IF(M21=0,"BM is $0",(AK21-M21)/M21)) -> 0
A27: DIGITAL PRESSES (A4 Size - One Side - Includes Paper) | K27: MAKE-READY | M27: PER/M | O27: =K27 -> MAKE-READY | Q27: =M27 -> PER/M | S27: =K27 -> MAKE-READY | U27: =M27 -> PER/M | W27: =K27 -> MAKE-READY | Y27: =M27 -> PER/M | AA27: =K27 -> MAKE-READY | AC27: =M27 -> PER/M | AE27: =O27 -> MAKE-READY | AG27: =M27 -> PER/M | AI27: =K27 -> MAKE-READY | AK27: =M27 -> PER/M | AM27: =K27 -> MAKE-READY | AO27: =M27 -> PER/M
A28: T-SERIES - Inkjet
A29: 0c Print 50lb - 60lb text | K29: 50 | M29: 3 | O29: 35 | Q29: 3 | S29: 0 | U29: 2 | AA29: =$K29*(1+$AI$2) -> 60 | AC29: =$M29*(1+$AK$2) -> 3.6 | AE29: =$O29*(1+$AI$2) -> 42 | AG29: =$Q29*(1+$AK$2) -> 3.6 | AI29: =IF(ISBLANK(W29),VLOOKUP(A29,A29:AG29,VLOOKUP($S$1,'Price Schedule (2)'!$BA$2:$BC$6,2,FALSE),FALSE),W29) -> 35 | AK29: =IF(ISBLANK(Y29),VLOOKUP(A29,A29:AG29,VLOOKUP($S$1,'Price Schedule (2)'!$BA$2:$BC$6,3,FALSE),FALSE),Y29) -> 3 | AM29: =IF(AND(K29=0,W29=0),0,IF(K29=0,"BM is $0",(AI29-K29)/K29)) -> -0.3 | AO29: =IF(AND(M29=0,Y29=0),0,IF(M29=0,"BM is $0",(AK29-M29)/M29)) -> 0
A30: 1c Print 50lb - 60lb text, light ink (<10%) | K30: 50 | M30: 10 | O30: 35 | Q30: 10 | S30: 0 | U30: 8 | AA30: =$K30*(1+$AI$2) -> 60 | AC30: =$M30*(1+$AK$2) -> 12 | AE30: =$O30*(1+$AI$2) -> 42 | AG30: =$Q30*(1+$AK$2) -> 12 | AI30: =IF(ISBLANK(W30),VLOOKUP(A30,A30:AG30,VLOOKUP($S$1,'Price Schedule (2)'!$BA$2:$BC$6,2,FALSE),FALSE),W30) -> 35 | AK30: =IF(ISBLANK(Y30),VLOOKUP(A30,A30:AG30,VLOOKUP($S$1,'Price Schedule (2)'!$BA$2:$BC$6,3,FALSE),FALSE),Y30) -> 10 | AM30: =IF(AND(K30=0,W30=0),0,IF(K30=0,"BM is $0",(AI30-K30)/K30)) -> -0.3 | AO30: =IF(AND(M30=0,Y30=0),0,IF(M30=0,"BM is $0",(AK30-M30)/M30)) -> 0
A31: 1c Print 50lb - 60lb text, medium ink (10% - 25%) | K31: 50 | M31: 15 | O31: 35 | Q31: 15 | S31: 0 | U31: 9 | AA31: =$K31*(1+$AI$2) -> 60 | AC31: =$M31*(1+$AK$2) -> 18 | AE31: =$O31*(1+$AI$2) -> 42 | AG31: =$Q31*(1+$AK$2) -> 18 | AI31: =IF(ISBLANK(W31),VLOOKUP(A31,A31:AG31,VLOOKUP($S$1,'Price Schedule (2)'!$BA$2:$BC$6,2,FALSE),FALSE),W31) -> 35 | AK31: =IF(ISBLANK(Y31),VLOOKUP(A31,A31:AG31,VLOOKUP($S$1,'Price Schedule (2)'!$BA$2:$BC$6,3,FALSE),FALSE),Y31) -> 15 | AM31: =IF(AND(K31=0,W31=0),0,IF(K31=0,"BM is $0",(AI31-K31)/K31)) -> -0.3 | AO31: =IF(AND(M31=0,Y31=0),0,IF(M31=0,"BM is $0",(AK31-M31)/M31)) -> 0
A32: 4c Print 50lb - 60lb text, light ink (<10%) | K32: 50 | M32: 20 | O32: 35 | Q32: 20 | S32: 0 | U32: 13 | AA32: =$K32*(1+$AI$2) -> 60 | AC32: =$M32*(1+$AK$2) -> 24 | AE32: =$O32*(1+$AI$2) -> 42 | AG32: =$Q32*(1+$AK$2) -> 24 | AI32: =IF(ISBLANK(W32),VLOOKUP(A32,A32:AG32,VLOOKUP($S$1,'Price Schedule (2)'!$BA$2:$BC$6,2,FALSE),FALSE),W32) -> 35 | AK32: =IF(ISBLANK(Y32),VLOOKUP(A32,A32:AG32,VLOOKUP($S$1,'Price Schedule (2)'!$BA$2:$BC$6,3,FALSE),FALSE),Y32) -> 20 | AM32: =IF(AND(K32=0,W32=0),0,IF(K32=0,"BM is $0",(AI32-K32)/K32)) -> -0.3 | AO32: =IF(AND(M32=0,Y32=0),0,IF(M32=0,"BM is $0",(AK32-M32)/M32)) -> 0
A33: 4c Print 50lb - 60lb text, medium ink (10% - 25%) | K33: 50 | M33: 22 | O33: 35 | Q33: 22 | S33: 0 | U33: 14 | AA33: =$K33*(1+$AI$2) -> 60 | AC33: =$M33*(1+$AK$2) -> 26.4 | AE33: =$O33*(1+$AI$2) -> 42 | AG33: =$Q33*(1+$AK$2) -> 26.4 | AI33: =IF(ISBLANK(W33),VLOOKUP(A33,A33:AG33,VLOOKUP($S$1,'Price Schedule (2)'!$BA$2:$BC$6,2,FALSE),FALSE),W33) -> 35 | AK33: =IF(ISBLANK(Y33),VLOOKUP(A33,A33:AG33,VLOOKUP($S$1,'Price Schedule (2)'!$BA$2:$BC$6,3,FALSE),FALSE),Y33) -> 22 | AM33: =IF(AND(K33=0,W33=0),0,IF(K33=0,"BM is $0",(AI33-K33)/K33)) -> -0.3 | AO33: =IF(AND(M33=0,Y33=0),0,IF(M33=0,"BM is $0",(AK33-M33)/M33)) -> 0
A34: 4c Print 50lb - 60lb text, heavy ink (25% - 50%) | K34: 50 | M34: 25 | O34: 35 | Q34: 25 | S34: 0 | U34: 15 | AA34: =$K34*(1+$AI$2) -> 60 | AC34: =$M34*(1+$AK$2) -> 30 | AE34: =$O34*(1+$AI$2) -> 42 | AG34: =$Q34*(1+$AK$2) -> 30 | AI34: =IF(ISBLANK(W34),VLOOKUP(A34,A34:AG34,VLOOKUP($S$1,'Price Schedule (2)'!$BA$2:$BC$6,2,FALSE),FALSE),W34) -> 35 | AK34: =IF(ISBLANK(Y34),VLOOKUP(A34,A34:AG34,VLOOKUP($S$1,'Price Schedule (2)'!$BA$2:$BC$6,3,FALSE),FALSE),Y34) -> 25 | AM34: =IF(AND(K34=0,W34=0),0,IF(K34=0,"BM is $0",(AI34-K34)/K34)) -> -0.3 | AO34: =IF(AND(M34=0,Y34=0),0,IF(M34=0,"BM is $0",(AK34-M34)/M34)) -> 0
A35: 0c Print 70lb - 100lb text | K35: 50 | M35: 13 | O35: 35 | Q35: 13 | S35: 0 | U35: 12 | AA35: =$K35*(1+$AI$2) -> 60 | AC35: =$M35*(1+$AK$2) -> 15.6 | AE35: =$O35*(1+$AI$2) -> 42 | AG35: =$Q35*(1+$AK$2) -> 15.6 | AI35: =IF(ISBLANK(W35),VLOOKUP(A35,A35:AG35,VLOOKUP($S$1,'Price Schedule (2)'!$BA$2:$BC$6,2,FALSE),FALSE),W35) -> 35 | AK35: =IF(ISBLANK(Y35),VLOOKUP(A35,A35:AG35,VLOOKUP($S$1,'Price Schedule (2)'!$BA$2:$BC$6,3,FALSE),FALSE),Y35) -> 13 | AM35: =IF(AND(K35=0,W35=0),0,IF(K35=0,"BM is $0",(AI35-K35)/K35)) -> -0.3 | AO35: =IF(AND(M35=0,Y35=0),0,IF(M35=0,"BM is $0",(AK35-M35)/M35)) -> 0
A36: 1c Print 70lb - 100lb text, light ink (<10%) | K36: 50 | M36: 20 | O36: 35 | Q36: 20 | S36: 0 | U36: 18 | AA36: =$K36*(1+$AI$2) -> 60 | AC36: =$M36*(1+$AK$2) -> 24 | AE36: =$O36*(1+$AI$2) -> 42 | AG36: =$Q36*(1+$AK$2) -> 24 | AI36: =IF(ISBLANK(W36),VLOOKUP(A36,A36:AG36,VLOOKUP($S$1,'Price Schedule (2)'!$BA$2:$BC$6,2,FALSE),FALSE),W36) -> 35 | AK36: =IF(ISBLANK(Y36),VLOOKUP(A36,A36:AG36,VLOOKUP($S$1,'Price Schedule (2)'!$BA$2:$BC$6,3,FALSE),FALSE),Y36) -> 20 | AM36: =IF(AND(K36=0,W36=0),0,IF(K36=0,"BM is $0",(AI36-K36)/K36)) -> -0.3 | AO36: =IF(AND(M36=0,Y36=0),0,IF(M36=0,"BM is $0",(AK36-M36)/M36)) -> 0
A37: 1c Print 70lb - 100lb text, medium ink (10% - 25%) | K37: 50 | M37: 24 | O37: 35 | Q37: 24 | S37: 0 | U37: 19 | AA37: =$K37*(1+$AI$2) -> 60 | AC37: =$M37*(1+$AK$2) -> 28.8 | AE37: =$O37*(1+$AI$2) -> 42 | AG37: =$Q37*(1+$AK$2) -> 28.8 | AI37: =IF(ISBLANK(W37),VLOOKUP(A37,A37:AG37,VLOOKUP($S$1,'Price Schedule (2)'!$BA$2:$BC$6,2,FALSE),FALSE),W37) -> 35 | AK37: =IF(ISBLANK(Y37),VLOOKUP(A37,A37:AG37,VLOOKUP($S$1,'Price Schedule (2)'!$BA$2:$BC$6,3,FALSE),FALSE),Y37) -> 24 | AM37: =IF(AND(K37=0,W37=0),0,IF(K37=0,"BM is $0",(AI37-K37)/K37)) -> -0.3 | AO37: =IF(AND(M37=0,Y37=0),0,IF(M37=0,"BM is $0",(AK37-M37)/M37)) -> 0
A38: 4c Print 70lb - 100lb text, light ink (<10%) | K38: 50 | M38: 30 | O38: 35 | Q38: 30 | S38: 0 | U38: 23 | AA38: =$K38*(1+$AI$2) -> 60 | AC38: =$M38*(1+$AK$2) -> 36 | AE38: =$O38*(1+$AI$2) -> 42 | AG38: =$Q38*(1+$AK$2) -> 36 | AI38: =IF(ISBLANK(W38),VLOOKUP(A38,A38:AG38,VLOOKUP($S$1,'Price Schedule (2)'!$BA$2:$BC$6,2,FALSE),FALSE),W38) -> 35 | AK38: =IF(ISBLANK(Y38),VLOOKUP(A38,A38:AG38,VLOOKUP($S$1,'Price Schedule (2)'!$BA$2:$BC$6,3,FALSE),FALSE),Y38) -> 30 | AM38: =IF(AND(K38=0,W38=0),0,IF(K38=0,"BM is $0",(AI38-K38)/K38)) -> -0.3 | AO38: =IF(AND(M38=0,Y38=0),0,IF(M38=0,"BM is $0",(AK38-M38)/M38)) -> 0
A39: 4c Print 70lb - 100lb text, medium ink (10% - 25%) | K39: 50 | M39: 32 | O39: 35 | Q39: 32 | S39: 0 | U39: 24 | AA39: =$K39*(1+$AI$2) -> 60 | AC39: =$M39*(1+$AK$2) -> 38.4 | AE39: =$O39*(1+$AI$2) -> 42 | AG39: =$Q39*(1+$AK$2) -> 38.4 | AI39: =IF(ISBLANK(W39),VLOOKUP(A39,A39:AG39,VLOOKUP($S$1,'Price Schedule (2)'!$BA$2:$BC$6,2,FALSE),FALSE),W39) -> 35 | AK39: =IF(ISBLANK(Y39),VLOOKUP(A39,A39:AG39,VLOOKUP($S$1,'Price Schedule (2)'!$BA$2:$BC$6,3,FALSE),FALSE),Y39) -> 32 | AM39: =IF(AND(K39=0,W39=0),0,IF(K39=0,"BM is $0",(AI39-K39)/K39)) -> -0.3 | AO39: =IF(AND(M39=0,Y39=0),0,IF(M39=0,"BM is $0",(AK39-M39)/M39)) -> 0
A40: 4c Print 70lb - 100lb text, heavy ink (25% - 50%) | K40: 50 | M40: 35 | O40: 35 | Q40: 35 | S40: 0 | U40: 25 | AA40: =$K40*(1+$AI$2) -> 60 | AC40: =$M40*(1+$AK$2) -> 42 | AE40: =$O40*(1+$AI$2) -> 42 | AG40: =$Q40*(1+$AK$2) -> 42 | AI40: =IF(ISBLANK(W40),VLOOKUP(A40,A40:AG40,VLOOKUP($S$1,'Price Schedule (2)'!$BA$2:$BC$6,2,FALSE),FALSE),W40) -> 35 | AK40: =IF(ISBLANK(Y40),VLOOKUP(A40,A40:AG40,VLOOKUP($S$1,'Price Schedule (2)'!$BA$2:$BC$6,3,FALSE),FALSE),Y40) -> 35 | AM40: =IF(AND(K40=0,W40=0),0,IF(K40=0,"BM is $0",(AI40-K40)/K40)) -> -0.3 | AO40: =IF(AND(M40=0,Y40=0),0,IF(M40=0,"BM is $0",(AK40-M40)/M40)) -> 0
A41: LIQUID TONER PRESSES (Includes J-Press and F-Press)
AA53: =$K53*(1+$AI$2) -> 0 | AC53: =$M53*(1+$AK$2) -> 0 | AE53: =$O53*(1+$AI$2) -> 0 | AG53: =$Q53*(1+$AK$2) -> 0 | AI53: =IF(ISBLANK(W53),VLOOKUP(A53,A53:AG53,VLOOKUP($S$1,'Price Schedule (2)'!$BA$2:$BC$6,2,FALSE),FALSE),W53) -> 0 | AK53: =IF(ISBLANK(Y53),VLOOKUP(A53,A53:AG53,VLOOKUP($S$1,'Price Schedule (2)'!$BA$2:$BC$6,3,FALSE),FALSE),Y53) -> 0 | AM53: =IF(AND(K53=0,W53=0),0,IF(K53=0,"BM is $0",(AI53-K53)/K53)) -> 0 | AO53: =IF(AND(M53=0,Y53=0),0,IF(M53=0,"BM is $0",(AK53-M53)/M53)) -> 0
A54: OFFLINE - DIGITAL SPECIFIC | K54: MAKE-READY | M54: PER/M | O54: =K54 -> MAKE-READY | Q54: =M54 -> PER/M | S54: =K54 -> MAKE-READY | U54: =M54 -> PER/M | W54: =K54 -> MAKE-READY | Y54: =M54 -> PER/M | AA54: =K54 -> MAKE-READY | AC54: =M54 -> PER/M | AE54: =O54 -> MAKE-READY | AG54: =M54 -> PER/M | AI54: =K54 -> MAKE-READY | AK54: =M54 -> PER/M | AM54: =K54 -> MAKE-READY | AO54: =M54 -> PER/M
A55: PRESS HOLDING TIME - /Hr Inkjet | K55: 200 | M55: 0 | O55: =K55 -> 200 | Q55: =M55 -> 0 | S55: 200 | AA55: =$K55*(1+$AI$2) -> 240 | AC55: =$M55*(1+$AK$2) -> 0 | AE55: =$O55*(1+$AI$2) -> 240 | AG55: =$Q55*(1+$AK$2) -> 0 | AI55: =IF(ISBLANK(W55),VLOOKUP(A55,A55:AG55,VLOOKUP($S$1,'Price Schedule (2)'!$BA$2:$BC$6,2,FALSE),FALSE),W55) -> 200 | AK55: =IF(ISBLANK(Y55),VLOOKUP(A55,A55:AG55,VLOOKUP($S$1,'Price Schedule (2)'!$BA$2:$BC$6,3,FALSE),FALSE),Y55) -> 0 | AM55: =IF(AND(K55=0,W55=0),0,IF(K55=0,"BM is $0",(AI55-K55)/K55)) -> 0 | AO55: =IF(AND(M55=0,Y55=0),0,IF(M55=0,"BM is $0",(AK55-M55)/M55)) -> 0
A56: PRESS HOLDING TIME - /Hr Liquid Toner | K56: 350 | M56: 0 | O56: =K56 -> 350 | Q56: =M56 -> 0 | S56: 350 | AA56: =$K56*(1+$AI$2) -> 420 | AC56: =$M56*(1+$AK$2) -> 0 | AE56: =$O56*(1+$AI$2) -> 420 | AG56: =$Q56*(1+$AK$2) -> 0 | AI56: =IF(ISBLANK(W56),VLOOKUP(A56,A56:AG56,VLOOKUP($S$1,'Price Schedule (2)'!$BA$2:$BC$6,2,FALSE),FALSE),W56) -> 350 | AK56: =IF(ISBLANK(Y56),VLOOKUP(A56,A56:AG56,VLOOKUP($S$1,'Price Schedule (2)'!$BA$2:$BC$6,3,FALSE),FALSE),Y56) -> 0 | AM56: =IF(AND(K56=0,W56=0),0,IF(K56=0,"BM is $0",(AI56-K56)/K56)) -> 0 | AO56: =IF(AND(M56=0,Y56=0),0,IF(M56=0,"BM is $0",(AK56-M56)/M56)) -> 0
A57: FLOOD GLOSS UV | K57: 300 | M57: 10 | O57: =K57 -> 300 | Q57: =M57 -> 10 | AA57: =$K57*(1+$AI$2) -> 360 | AC57: =$M57*(1+$AK$2) -> 12 | AE57: =$O57*(1+$AI$2) -> 360 | AG57: =$Q57*(1+$AK$2) -> 12 | AI57: =IF(ISBLANK(W57),VLOOKUP(A57,A57:AG57,VLOOKUP($S$1,'Price Schedule (2)'!$BA$2:$BC$6,2,FALSE),FALSE),W57) -> 300 | AK57: =IF(ISBLANK(Y57),VLOOKUP(A57,A57:AG57,VLOOKUP($S$1,'Price Schedule (2)'!$BA$2:$BC$6,3,FALSE),FALSE),Y57) -> 10 | AM57: =IF(AND(K57=0,W57=0),0,IF(K57=0,"BM is $0",(AI57-K57)/K57)) -> 0 | AO57: =IF(AND(M57=0,Y57=0),0,IF(M57=0,"BM is $0",(AK57-M57)/M57)) -> 0
A58: FLOOD MATTE UV | K58: 300 | M58: 12 | O58: =K58 -> 300 | Q58: =M58 -> 12 | AA58: =$K58*(1+$AI$2) -> 360 | AC58: =$M58*(1+$AK$2) -> 14.4 | AE58: =$O58*(1+$AI$2) -> 360 | AG58: =$Q58*(1+$AK$2) -> 14.4 | AI58: =IF(ISBLANK(W58),VLOOKUP(A58,A58:AG58,VLOOKUP($S$1,'Price Schedule (2)'!$BA$2:$BC$6,2,FALSE),FALSE),W58) -> 300 | AK58: =IF(ISBLANK(Y58),VLOOKUP(A58,A58:AG58,VLOOKUP($S$1,'Price Schedule (2)'!$BA$2:$BC$6,3,FALSE),FALSE),Y58) -> 12 | AM58: =IF(AND(K58=0,W58=0),0,IF(K58=0,"BM is $0",(AI58-K58)/K58)) -> 0 | AO58: =IF(AND(M58=0,Y58=0),0,IF(M58=0,"BM is $0",(AK58-M58)/M58)) -> 0
A59: FLOOD SATIN UV | K59: 300 | M59: 12 | O59: =K59 -> 300 | Q59: =M59 -> 12 | AA59: =$K59*(1+$AI$2) -> 360 | AC59: =$M59*(1+$AK$2) -> 14.4 | AE59: =$O59*(1+$AI$2) -> 360 | AG59: =$Q59*(1+$AK$2) -> 14.4 | AI59: =IF(ISBLANK(W59),VLOOKUP(A59,A59:AG59,VLOOKUP($S$1,'Price Schedule (2)'!$BA$2:$BC$6,2,FALSE),FALSE),W59) -> 300 | AK59: =IF(ISBLANK(Y59),VLOOKUP(A59,A59:AG59,VLOOKUP($S$1,'Price Schedule (2)'!$BA$2:$BC$6,3,FALSE),FALSE),Y59) -> 12 | AM59: =IF(AND(K59=0,W59=0),0,IF(K59=0,"BM is $0",(AI59-K59)/K59)) -> 0 | AO59: =IF(AND(M59=0,Y59=0),0,IF(M59=0,"BM is $0",(AK59-M59)/M59)) -> 0
A60: FLOOD SOFT TOUCH UV | K60: 300 | M60: 17.5 | O60: =K60 -> 300 | Q60: =M60 -> 17.5 | AA60: =$K60*(1+$AI$2) -> 360 | AC60: =$M60*(1+$AK$2) -> 21 | AE60: =$O60*(1+$AI$2) -> 360 | AG60: =$Q60*(1+$AK$2) -> 21 | AI60: =IF(ISBLANK(W60),VLOOKUP(A60,A60:AG60,VLOOKUP($S$1,'Price Schedule (2)'!$BA$2:$BC$6,2,FALSE),FALSE),W60) -> 300 | AK60: =IF(ISBLANK(Y60),VLOOKUP(A60,A60:AG60,VLOOKUP($S$1,'Price Schedule (2)'!$BA$2:$BC$6,3,FALSE),FALSE),Y60) -> 17.5 | AM60: =IF(AND(K60=0,W60=0),0,IF(K60=0,"BM is $0",(AI60-K60)/K60)) -> 0 | AO60: =IF(AND(M60=0,Y60=0),0,IF(M60=0,"BM is $0",(AK60-M60)/M60)) -> 0
A61: PATTERN UV (Non-Registered) | K61: 0 | M61: 0 | O61: =K61 -> 0 | Q61: =M61 -> 0 | AA61: =$K61*(1+$AI$2) -> 0 | AC61: =$M61*(1+$AK$2) -> 0 | AE61: =$O61*(1+$AI$2) -> 0 | AG61: =$Q61*(1+$AK$2) -> 0 | AI61: =IF(ISBLANK(W61),VLOOKUP(A61,A61:AG61,VLOOKUP($S$1,'Price Schedule (2)'!$BA$2:$BC$6,2,FALSE),FALSE),W61) -> 0 | AK61: =IF(ISBLANK(Y61),VLOOKUP(A61,A61:AG61,VLOOKUP($S$1,'Price Schedule (2)'!$BA$2:$BC$6,3,FALSE),FALSE),Y61) -> 0 | AM61: =IF(AND(K61=0,W61=0),0,IF(K61=0,"BM is $0",(AI61-K61)/K61)) -> 0 | AO61: =IF(AND(M61=0,Y61=0),0,IF(M61=0,"BM is $0",(AK61-M61)/M61)) -> 0
A62: REGISTERED UV | K62: 0 | M62: 0 | O62: =K62 -> 0 | Q62: =M62 -> 0 | AA62: =$K62*(1+$AI$2) -> 0 | AC62: =$M62*(1+$AK$2) -> 0 | AE62: =$O62*(1+$AI$2) -> 0 | AG62: =$Q62*(1+$AK$2) -> 0 | AI62: =IF(ISBLANK(W62),VLOOKUP(A62,A62:AG62,VLOOKUP($S$1,'Price Schedule (2)'!$BA$2:$BC$6,2,FALSE),FALSE),W62) -> 0 | AK62: =IF(ISBLANK(Y62),VLOOKUP(A62,A62:AG62,VLOOKUP($S$1,'Price Schedule (2)'!$BA$2:$BC$6,3,FALSE),FALSE),Y62) -> 0 | AM62: =IF(AND(K62=0,W62=0),0,IF(K62=0,"BM is $0",(AI62-K62)/K62)) -> 0 | AO62: =IF(AND(M62=0,Y62=0),0,IF(M62=0,"BM is $0",(AK62-M62)/M62)) -> 0
A63: FLOOD SPECIALTY UV | K63: 0 | M63: 0 | O63: =K63 -> 0 | Q63: =M63 -> 0 | AA63: =$K63*(1+$AI$2) -> 0 | AC63: =$M63*(1+$AK$2) -> 0 | AE63: =$O63*(1+$AI$2) -> 0 | AG63: =$Q63*(1+$AK$2) -> 0 | AI63: =IF(ISBLANK(W63),VLOOKUP(A63,A63:AG63,VLOOKUP($S$1,'Price Schedule (2)'!$BA$2:$BC$6,2,FALSE),FALSE),W63) -> 0 | AK63: =IF(ISBLANK(Y63),VLOOKUP(A63,A63:AG63,VLOOKUP($S$1,'Price Schedule (2)'!$BA$2:$BC$6,3,FALSE),FALSE),Y63) -> 0 | AM63: =IF(AND(K63=0,W63=0),0,IF(K63=0,"BM is $0",(AI63-K63)/K63)) -> 0 | AO63: =IF(AND(M63=0,Y63=0),0,IF(M63=0,"BM is $0",(AK63-M63)/M63)) -> 0
AA64: =$K64*(1+$AI$2) -> 0 | AC64: =$M64*(1+$AK$2) -> 0 | AE64: =$O64*(1+$AI$2) -> 0 | AG64: =$Q64*(1+$AK$2) -> 0 | AI64: =IF(ISBLANK(W64),VLOOKUP(A64,A64:AG64,VLOOKUP($S$1,'Price Schedule (2)'!$BA$2:$BC$6,2,FALSE),FALSE),W64) -> 0 | AK64: =IF(ISBLANK(Y64),VLOOKUP(A64,A64:AG64,VLOOKUP($S$1,'Price Schedule (2)'!$BA$2:$BC$6,3,FALSE),FALSE),Y64) -> 0 | AM64: =IF(AND(K64=0,W64=0),0,IF(K64=0,"BM is $0",(AI64-K64)/K64)) -> 0 | AO64: =IF(AND(M64=0,Y64=0),0,IF(M64=0,"BM is $0",(AK64-M64)/M64)) -> 0
A65: SHEETFED PRESSWORK | K65: MAKE-READY | M65: PER/M | O65: =K65 -> MAKE-READY | Q65: =M65 -> PER/M | S65: =K65 -> MAKE-READY | U65: =M65 -> PER/M | W65: =K65 -> MAKE-READY | Y65: =M65 -> PER/M | AA65: =K65 -> MAKE-READY | AC65: =M65 -> PER/M | AE65: =O65 -> MAKE-READY | AG65: =M65 -> PER/M | AI65: =K65 -> MAKE-READY | AK65: =M65 -> PER/M | AM65: =K65 -> MAKE-READY | AO65: =M65 -> PER/M
A66: BASE PRESS | B66: 47 | C66: x | D66: 64 | O66: =K66 -> 0 | Q66: =M66 -> 0 | AA66: =$K66*(1+$AI$2) -> 0 | AC66: =$M66*(1+$AK$2) -> 0 | AE66: =$O66*(1+$AI$2) -> 0 | AG66: =$Q66*(1+$AK$2) -> 0 | AI66: =IF(ISBLANK(W66),VLOOKUP(A66,A66:AG66,VLOOKUP($S$1,'Price Schedule (2)'!$BA$2:$BC$6,2,FALSE),FALSE),W66) -> 0 | AK66: =IF(ISBLANK(Y66),VLOOKUP(A66,A66:AG66,VLOOKUP($S$1,'Price Schedule (2)'!$BA$2:$BC$6,3,FALSE),FALSE),Y66) -> 0 | AM66: =IF(AND(K66=0,W66=0),0,IF(K66=0,"BM is $0",(AI66-K66)/K66)) -> 0 | AO66: =IF(AND(M66=0,Y66=0),0,IF(M66=0,"BM is $0",(AK66-M66)/M66)) -> 0
A67: PER PLATE | B67: 47 | C67: x | D67: 64 | O67: =K67 -> 0 | Q67: =M67 -> 0 | AA67: =$K67*(1+$AI$2) -> 0 | AC67: =$M67*(1+$AK$2) -> 0 | AE67: =$O67*(1+$AI$2) -> 0 | AG67: =$Q67*(1+$AK$2) -> 0 | AI67: =IF(ISBLANK(W67),VLOOKUP(A67,A67:AG67,VLOOKUP($S$1,'Price Schedule (2)'!$BA$2:$BC$6,2,FALSE),FALSE),W67) -> 0 | AK67: =IF(ISBLANK(Y67),VLOOKUP(A67,A67:AG67,VLOOKUP($S$1,'Price Schedule (2)'!$BA$2:$BC$6,3,FALSE),FALSE),Y67) -> 0 | AM67: =IF(AND(K67=0,W67=0),0,IF(K67=0,"BM is $0",(AI67-K67)/K67)) -> 0 | AO67: =IF(AND(M67=0,Y67=0),0,IF(M67=0,"BM is $0",(AK67-M67)/M67)) -> 0
A68: BASE PRESS | B68: 28 | C68: x | D68: 40 | K68: 200 | M68: 61.75 | O68: 200 | Q68: 44.1 | S68: 150 | U68: 28.7 | AA68: =$K68*(1+$AI$2) -> 240 | AC68: =$M68*(1+$AK$2) -> 74.1 | AE68: =$O68*(1+$AI$2) -> 240 | AG68: =$Q68*(1+$AK$2) -> 52.92 | AI68: =IF(ISBLANK(W68),VLOOKUP(A68,A68:AG68,VLOOKUP($S$1,'Price Schedule (2)'!$BA$2:$BC$6,2,FALSE),FALSE),W68) -> 200 | AK68: =IF(ISBLANK(Y68),VLOOKUP(A68,A68:AG68,VLOOKUP($S$1,'Price Schedule (2)'!$BA$2:$BC$6,3,FALSE),FALSE),Y68) -> 44.1 | AM68: =IF(AND(K68=0,W68=0),0,IF(K68=0,"BM is $0",(AI68-K68)/K68)) -> 0 | AO68: =IF(AND(M68=0,Y68=0),0,IF(M68=0,"BM is $0",(AK68-M68)/M68)) -> -0.28582996
A69: PER PLATE | B69: 28 | C69: x | D69: 40 | K69: =120+10 -> 130 | M69: 0 | O69: =95+10 -> 105 | Q69: =M69 -> 0 | S69: =65+10 -> 75 | U69: 0 | AA69: =$K69*(1+$AI$2) -> 156 | AC69: =$M69*(1+$AK$2) -> 0 | AE69: =$O69*(1+$AI$2) -> 126 | AG69: =$Q69*(1+$AK$2) -> 0 | AI69: =IF(ISBLANK(W69),VLOOKUP(A69,A69:AG69,VLOOKUP($S$1,'Price Schedule (2)'!$BA$2:$BC$6,2,FALSE),FALSE),W69) -> 105 | AK69: =IF(ISBLANK(Y69),VLOOKUP(A69,A69:AG69,VLOOKUP($S$1,'Price Schedule (2)'!$BA$2:$BC$6,3,FALSE),FALSE),Y69) -> 0 | AM69: =IF(AND(K69=0,W69=0),0,IF(K69=0,"BM is $0",(AI69-K69)/K69)) -> -0.19230769 | AO69: =IF(AND(M69=0,Y69=0),0,IF(M69=0,"BM is $0",(AK69-M69)/M69)) -> 0
A70: SHEETFED PRESSWORK MISC. SERVICE | K70: MAKE-READY | M70: PER/M | O70: =K70 -> MAKE-READY | Q70: =M70 -> PER/M | S70: =K70 -> MAKE-READY | U70: =M70 -> PER/M | W70: =K70 -> MAKE-READY | Y70: =M70 -> PER/M | AA70: =K70 -> MAKE-READY | AC70: =M70 -> PER/M | AE70: =O70 -> MAKE-READY | AG70: =M70 -> PER/M | AI70: =K70 -> MAKE-READY | AK70: =M70 -> PER/M | AM70: =K70 -> MAKE-READY | AO70: =M70 -> PER/M
A71: INLINE AQUEOUS - IMPRESSION (per side) | K71: 125 | M71: 7.75 | O71: 85 | Q71: 6.25 | S71: 50 | U71: 5.8 | AA71: =$K71*(1+$AI$2) -> 150 | AC71: =$M71*(1+$AK$2) -> 9.3 | AE71: =$O71*(1+$AI$2) -> 102 | AG71: =$Q71*(1+$AK$2) -> 7.5 | AI71: =IF(ISBLANK(W71),VLOOKUP(A71,A71:AG71,VLOOKUP($S$1,'Price Schedule (2)'!$BA$2:$BC$6,2,FALSE),FALSE),W71) -> 85 | AK71: =IF(ISBLANK(Y71),VLOOKUP(A71,A71:AG71,VLOOKUP($S$1,'Price Schedule (2)'!$BA$2:$BC$6,3,FALSE),FALSE),Y71) -> 6.25 | AM71: =IF(AND(K71=0,W71=0),0,IF(K71=0,"BM is $0",(AI71-K71)/K71)) -> -0.32 | AO71: =IF(AND(M71=0,Y71=0),0,IF(M71=0,"BM is $0",(AK71-M71)/M71)) -> -0.19354839
A72: GLOSS AQUEOUS - MATERIAL (per square inch) | K72: 0 | M72: =0.2256*1.15 -> 0.25944 | O72: 0 | Q72: =M72 -> 0.25944 | S72: 0 | U72: =M72 -> 0.25944 | AA72: =$K72*(1+$AI$2) -> 0 | AC72: =$M72 -> 0.25944 | AE72: =$O72 -> 0 | AG72: =$Q72 -> 0.25944 | AI72: =IF(ISBLANK(W72),VLOOKUP(A72,A72:AG72,VLOOKUP($S$1,'Price Schedule (2)'!$BA$2:$BC$6,2,FALSE),FALSE),W72) -> 0 | AK72: =IF(ISBLANK(Y72),VLOOKUP(A72,A72:AG72,VLOOKUP($S$1,'Price Schedule (2)'!$BA$2:$BC$6,3,FALSE),FALSE),Y72) -> 0.25944 | AM72: =IF(AND(K72=0,W72=0),0,IF(K72=0,"BM is $0",(AI72-K72)/K72)) -> 0 | AO72: =IF(AND(M72=0,Y72=0),0,IF(M72=0,"BM is $0",(AK72-M72)/M72)) -> 0
A73: MATTE/SATIN/DULL AQUEOUS - MATERIAL (per square inch) | K73: 0 | M73: =0.0252*1.15 -> 0.02898 | O73: 0 | Q73: =M73 -> 0.02898 | S73: 0 | U73: =M73 -> 0.02898 | AA73: =$K73*(1+$AI$2) -> 0 | AC73: =$M73 -> 0.02898 | AE73: =$O73 -> 0 | AG73: =$Q73 -> 0.02898 | AI73: =IF(ISBLANK(W73),VLOOKUP(A73,A73:AG73,VLOOKUP($S$1,'Price Schedule (2)'!$BA$2:$BC$6,2,FALSE),FALSE),W73) -> 0 | AK73: =IF(ISBLANK(Y73),VLOOKUP(A73,A73:AG73,VLOOKUP($S$1,'Price Schedule (2)'!$BA$2:$BC$6,3,FALSE),FALSE),Y73) -> 0.02898 | AM73: =IF(AND(K73=0,W73=0),0,IF(K73=0,"BM is $0",(AI73-K73)/K73)) -> 0 | AO73: =IF(AND(M73=0,Y73=0),0,IF(M73=0,"BM is $0",(AK73-M73)/M73)) -> 0
A74: SOFT TOUCH AQUEOUS - MATERIAL (per square inch) | K74: 75 | M74: =0.1377*1.15 -> 0.158355 | O74: 75 | Q74: =M74 -> 0.158355 | S74: 40 | U74: =M74 -> 0.158355 | AA74: =$K74*(1+$AI$2) -> 90 | AC74: =$M74 -> 0.158355 | AE74: =$O74 -> 75 | AG74: =$Q74 -> 0.158355 | AI74: =IF(ISBLANK(W74),VLOOKUP(A74,A74:AG74,VLOOKUP($S$1,'Price Schedule (2)'!$BA$2:$BC$6,2,FALSE),FALSE),W74) -> 75 | AK74: =IF(ISBLANK(Y74),VLOOKUP(A74,A74:AG74,VLOOKUP($S$1,'Price Schedule (2)'!$BA$2:$BC$6,3,FALSE),FALSE),Y74) -> 0.158355 | AM74: =IF(AND(K74=0,W74=0),0,IF(K74=0,"BM is $0",(AI74-K74)/K74)) -> 0 | AO74: =IF(AND(M74=0,Y74=0),0,IF(M74=0,"BM is $0",(AK74-M74)/M74)) -> 0
A75: CREDIT FOR PLATE NOT USED per plate | K75: -100 | M75: 0 | O75: -50 | Q75: 0 | S75: -35 | U75: 0 | AA75: =$K75*(1+$AI$2) -> -120 | AC75: =$M75*(1+$AK$2) -> 0 | AE75: =$O75*(1+$AI$2) -> -60 | AG75: =$Q75*(1+$AK$2) -> 0 | AI75: =IF(ISBLANK(W75),VLOOKUP(A75,A75:AG75,VLOOKUP($S$1,'Price Schedule (2)'!$BA$2:$BC$6,2,FALSE),FALSE),W75) -> -50 | AK75: =IF(ISBLANK(Y75),VLOOKUP(A75,A75:AG75,VLOOKUP($S$1,'Price Schedule (2)'!$BA$2:$BC$6,3,FALSE),FALSE),Y75) -> 0 | AM75: =IF(AND(K75=0,W75=0),0,IF(K75=0,"BM is $0",(AI75-K75)/K75)) -> -0.5 | AO75: =IF(AND(M75=0,Y75=0),0,IF(M75=0,"BM is $0",(AK75-M75)/M75)) -> 0
A76: HOLDING TIME per hour | K76: 550 | M76: 0 | O76: 400 | Q76: 0 | S76: 350 | U76: 0 | AA76: =$K76*(1+$AI$2) -> 660 | AC76: =$M76*(1+$AK$2) -> 0 | AE76: =$O76*(1+$AI$2) -> 480 | AG76: =$Q76*(1+$AK$2) -> 0 | AI76: =IF(ISBLANK(W76),VLOOKUP(A76,A76:AG76,VLOOKUP($S$1,'Price Schedule (2)'!$BA$2:$BC$6,2,FALSE),FALSE),W76) -> 400 | AK76: =IF(ISBLANK(Y76),VLOOKUP(A76,A76:AG76,VLOOKUP($S$1,'Price Schedule (2)'!$BA$2:$BC$6,3,FALSE),FALSE),Y76) -> 0 | AM76: =IF(AND(K76=0,W76=0),0,IF(K76=0,"BM is $0",(AI76-K76)/K76)) -> -0.27272727 | AO76: =IF(AND(M76=0,Y76=0),0,IF(M76=0,"BM is $0",(AK76-M76)/M76)) -> 0
A77: UNIT WASH-UP per unit | K77: 65 | M77: 0 | O77: 35 | Q77: 0 | S77: 0 | U77: 0 | AA77: =$K77*(1+$AI$2) -> 78 | AC77: =$M77*(1+$AK$2) -> 0 | AE77: =$O77*(1+$AI$2) -> 42 | AG77: =$Q77*(1+$AK$2) -> 0 | AI77: =IF(ISBLANK(W77),VLOOKUP(A77,A77:AG77,VLOOKUP($S$1,'Price Schedule (2)'!$BA$2:$BC$6,2,FALSE),FALSE),W77) -> 35 | AK77: =IF(ISBLANK(Y77),VLOOKUP(A77,A77:AG77,VLOOKUP($S$1,'Price Schedule (2)'!$BA$2:$BC$6,3,FALSE),FALSE),Y77) -> 0 | AM77: =IF(AND(K77=0,W77=0),0,IF(K77=0,"BM is $0",(AI77-K77)/K77)) -> -0.46153846 | AO77: =IF(AND(M77=0,Y77=0),0,IF(M77=0,"BM is $0",(AK77-M77)/M77)) -> 0
A78: PERF (Square Corners) | K78: 150 | M78: 3 | O78: 100 | Q78: 2.25 | S78: 50 | U78: 0.75 | AA78: =$K78*(1+$AI$2) -> 180 | AC78: =$M78*(1+$AK$2) -> 3.6 | AE78: =$O78*(1+$AI$2) -> 120 | AG78: =$Q78*(1+$AK$2) -> 2.7 | AI78: =IF(ISBLANK(W78),VLOOKUP(A78,A78:AG78,VLOOKUP($S$1,'Price Schedule (2)'!$BA$2:$BC$6,2,FALSE),FALSE),W78) -> 100 | AK78: =IF(ISBLANK(Y78),VLOOKUP(A78,A78:AG78,VLOOKUP($S$1,'Price Schedule (2)'!$BA$2:$BC$6,3,FALSE),FALSE),Y78) -> 2.25 | AM78: =IF(AND(K78=0,W78=0),0,IF(K78=0,"BM is $0",(AI78-K78)/K78)) -> -0.33333333 | AO78: =IF(AND(M78=0,Y78=0),0,IF(M78=0,"BM is $0",(AK78-M78)/M78)) -> -0.25
A79: ROLL TO SHEET CONVERT > 38" Rolls | K79: 100 | M79: 5.5 | O79: 50 | Q79: 4 | S79: 15 | U79: 1.25 | AA79: =$K79*(1+$AI$2) -> 120 | AC79: =$M79*(1+$AK$2) -> 6.6 | AE79: =$O79*(1+$AI$2) -> 60 | AG79: =$Q79*(1+$AK$2) -> 4.8 | AI79: =IF(ISBLANK(W79),VLOOKUP(A79,A79:AG79,VLOOKUP($S$1,'Price Schedule (2)'!$BA$2:$BC$6,2,FALSE),FALSE),W79) -> 50 | AK79: =IF(ISBLANK(Y79),VLOOKUP(A79,A79:AG79,VLOOKUP($S$1,'Price Schedule (2)'!$BA$2:$BC$6,3,FALSE),FALSE),Y79) -> 4 | AM79: =IF(AND(K79=0,W79=0),0,IF(K79=0,"BM is $0",(AI79-K79)/K79)) -> -0.5 | AO79: =IF(AND(M79=0,Y79=0),0,IF(M79=0,"BM is $0",(AK79-M79)/M79)) -> -0.27272727
A80: ROLL TO SHEET CONVERT ≤ 38" Rolls | K80: 100 | M80: 3.15 | O80: 50 | Q80: 3 | S80: 15 | U80: 1.25 | AA80: =$K80*(1+$AI$2) -> 120 | AC80: =$M80*(1+$AK$2) -> 3.78 | AE80: =$O80*(1+$AI$2) -> 60 | AG80: =$Q80*(1+$AK$2) -> 3.6 | AI80: =IF(ISBLANK(W80),VLOOKUP(A80,A80:AG80,VLOOKUP($S$1,'Price Schedule (2)'!$BA$2:$BC$6,2,FALSE),FALSE),W80) -> 50 | AK80: =IF(ISBLANK(Y80),VLOOKUP(A80,A80:AG80,VLOOKUP($S$1,'Price Schedule (2)'!$BA$2:$BC$6,3,FALSE),FALSE),Y80) -> 3 | AM80: =IF(AND(K80=0,W80=0),0,IF(K80=0,"BM is $0",(AI80-K80)/K80)) -> -0.5 | AO80: =IF(AND(M80=0,Y80=0),0,IF(M80=0,"BM is $0",(AK80-M80)/M80)) -> -0.047619048
A81: VERSION PLATE & MKR CHANGE per plate | K81: 125 | M81: 0 | O81: 75 | Q81: 0 | S81: 45 | U81: 0 | AA81: =$K81*(1+$AI$2) -> 150 | AC81: =$M81*(1+$AK$2) -> 0 | AE81: =$O81*(1+$AI$2) -> 90 | AG81: =$Q81*(1+$AK$2) -> 0 | AI81: =IF(ISBLANK(W81),VLOOKUP(A81,A81:AG81,VLOOKUP($S$1,'Price Schedule (2)'!$BA$2:$BC$6,2,FALSE),FALSE),W81) -> 75 | AK81: =IF(ISBLANK(Y81),VLOOKUP(A81,A81:AG81,VLOOKUP($S$1,'Price Schedule (2)'!$BA$2:$BC$6,3,FALSE),FALSE),Y81) -> 0 | AM81: =IF(AND(K81=0,W81=0),0,IF(K81=0,"BM is $0",(AI81-K81)/K81)) -> -0.4 | AO81: =IF(AND(M81=0,Y81=0),0,IF(M81=0,"BM is $0",(AK81-M81)/M81)) -> 0
A82: VERSION PLATE PRESS STOP per stop, per web | K82: 150 | M82: 0 | O82: 115 | Q82: 0 | S82: 35 | U82: 0 | AA82: =$K82*(1+$AI$2) -> 180 | AC82: =$M82*(1+$AK$2) -> 0 | AE82: =$O82*(1+$AI$2) -> 138 | AG82: =$Q82*(1+$AK$2) -> 0 | AI82: =IF(ISBLANK(W82),VLOOKUP(A82,A82:AG82,VLOOKUP($S$1,'Price Schedule (2)'!$BA$2:$BC$6,2,FALSE),FALSE),W82) -> 115 | AK82: =IF(ISBLANK(Y82),VLOOKUP(A82,A82:AG82,VLOOKUP($S$1,'Price Schedule (2)'!$BA$2:$BC$6,3,FALSE),FALSE),Y82) -> 0 | AM82: =IF(AND(K82=0,W82=0),0,IF(K82=0,"BM is $0",(AI82-K82)/K82)) -> -0.23333333 | AO82: =IF(AND(M82=0,Y82=0),0,IF(M82=0,"BM is $0",(AK82-M82)/M82)) -> 0
A83: N/A | K83: 0 | M83: 0 | O83: 0 | Q83: 0 | S83: 0 | U83: 0 | AA83: =$K83*(1+$AI$2) -> 0 | AC83: =$M83*(1+$AK$2) -> 0 | AE83: =$O83*(1+$AI$2) -> 0 | AG83: =$Q83*(1+$AK$2) -> 0 | AI83: =IF(ISBLANK(W83),VLOOKUP(A83,A83:AG83,VLOOKUP($S$1,'Price Schedule (2)'!$BA$2:$BC$6,2,FALSE),FALSE),W83) -> 0 | AK83: =IF(ISBLANK(Y83),VLOOKUP(A83,A83:AG83,VLOOKUP($S$1,'Price Schedule (2)'!$BA$2:$BC$6,3,FALSE),FALSE),Y83) -> 0 | AM83: =IF(AND(K83=0,W83=0),0,IF(K83=0,"BM is $0",(AI83-K83)/K83)) -> 0 | AO83: =IF(AND(M83=0,Y83=0),0,IF(M83=0,"BM is $0",(AK83-M83)/M83)) -> 0
A84: SANDEN PRESSWORK | K84: MAKE-READY | M84: PER/M | O84: =K84 -> MAKE-READY | Q84: =M84 -> PER/M | S84: =K84 -> MAKE-READY | U84: =M84 -> PER/M | W84: =K84 -> MAKE-READY | Y84: =M84 -> PER/M | AA84: =K84 -> MAKE-READY | AC84: =M84 -> PER/M | AE84: =O84 -> MAKE-READY | AG84: =M84 -> PER/M | AI84: =K84 -> MAKE-READY | AK84: =M84 -> PER/M | AM84: =K84 -> MAKE-READY | AO84: =M84 -> PER/M
A85: BASE PRESS - 22" cylinder per IMP | K85: 250 | M85: 16 | O85: 125 | Q85: 12 | S85: 75 | U85: 8 | AA85: =$K85*(1+$AI$2) -> 300 | AC85: =$M85*(1+$AK$2) -> 19.2 | AE85: =$O85*(1+$AI$2) -> 150 | AG85: =$Q85*(1+$AK$2) -> 14.4 | AI85: =IF(ISBLANK(W85),VLOOKUP(A85,A85:AG85,VLOOKUP($S$1,'Price Schedule (2)'!$BA$2:$BC$6,2,FALSE),FALSE),W85) -> 125 | AK85: =IF(ISBLANK(Y85),VLOOKUP(A85,A85:AG85,VLOOKUP($S$1,'Price Schedule (2)'!$BA$2:$BC$6,3,FALSE),FALSE),Y85) -> 12 | AM85: =IF(AND(K85=0,W85=0),0,IF(K85=0,"BM is $0",(AI85-K85)/K85)) -> -0.5 | AO85: =IF(AND(M85=0,Y85=0),0,IF(M85=0,"BM is $0",(AK85-M85)/M85)) -> -0.25
A86: BASE PRESS - 25.5" cylinder per IMP | K86: 250 | M86: 20 | O86: 125 | Q86: 14 | S86: 75 | U86: 10 | AA86: =$K86*(1+$AI$2) -> 300 | AC86: =$M86*(1+$AK$2) -> 24 | AE86: =$O86*(1+$AI$2) -> 150 | AG86: =$Q86*(1+$AK$2) -> 16.8 | AI86: =IF(ISBLANK(W86),VLOOKUP(A86,A86:AG86,VLOOKUP($S$1,'Price Schedule (2)'!$BA$2:$BC$6,2,FALSE),FALSE),W86) -> 125 | AK86: =IF(ISBLANK(Y86),VLOOKUP(A86,A86:AG86,VLOOKUP($S$1,'Price Schedule (2)'!$BA$2:$BC$6,3,FALSE),FALSE),Y86) -> 14 | AM86: =IF(AND(K86=0,W86=0),0,IF(K86=0,"BM is $0",(AI86-K86)/K86)) -> -0.5 | AO86: =IF(AND(M86=0,Y86=0),0,IF(M86=0,"BM is $0",(AK86-M86)/M86)) -> -0.3
A87: BASE PRESS - 28" cylinder per IMP | K87: 250 | M87: 22 | O87: 125 | Q87: 15.25 | S87: 75 | U87: 10.5 | AA87: =$K87*(1+$AI$2) -> 300 | AC87: =$M87*(1+$AK$2) -> 26.4 | AE87: =$O87*(1+$AI$2) -> 150 | AG87: =$Q87*(1+$AK$2) -> 18.3 | AI87: =IF(ISBLANK(W87),VLOOKUP(A87,A87:AG87,VLOOKUP($S$1,'Price Schedule (2)'!$BA$2:$BC$6,2,FALSE),FALSE),W87) -> 125 | AK87: =IF(ISBLANK(Y87),VLOOKUP(A87,A87:AG87,VLOOKUP($S$1,'Price Schedule (2)'!$BA$2:$BC$6,3,FALSE),FALSE),Y87) -> 15.25 | AM87: =IF(AND(K87=0,W87=0),0,IF(K87=0,"BM is $0",(AI87-K87)/K87)) -> -0.5 | AO87: =IF(AND(M87=0,Y87=0),0,IF(M87=0,"BM is $0",(AK87-M87)/M87)) -> -0.30681818
A88: PER PLATE | K88: 200 | M88: 1 | O88: 100 | Q88: 0.5 | S88: 60 | U88: 0.25 | AA88: =$K88*(1+$AI$2) -> 240 | AC88: =$M88*(1+$AK$2) -> 1.2 | AE88: =$O88*(1+$AI$2) -> 120 | AG88: =$Q88*(1+$AK$2) -> 0.6 | AI88: =IF(ISBLANK(W88),VLOOKUP(A88,A88:AG88,VLOOKUP($S$1,'Price Schedule (2)'!$BA$2:$BC$6,2,FALSE),FALSE),W88) -> 100 | AK88: =IF(ISBLANK(Y88),VLOOKUP(A88,A88:AG88,VLOOKUP($S$1,'Price Schedule (2)'!$BA$2:$BC$6,3,FALSE),FALSE),Y88) -> 0.5 | AM88: =IF(AND(K88=0,W88=0),0,IF(K88=0,"BM is $0",(AI88-K88)/K88)) -> -0.5 | AO88: =IF(AND(M88=0,Y88=0),0,IF(M88=0,"BM is $0",(AK88-M88)/M88)) -> -0.5
A89: SANDEN PRESSWORK MISC. SERVICE | K89: MAKE-READY | M89: PER/M | O89: =K89 -> MAKE-READY | Q89: =M89 -> PER/M | S89: =K89 -> MAKE-READY | U89: =M89 -> PER/M | W89: =K89 -> MAKE-READY | Y89: =M89 -> PER/M | AA89: =K89 -> MAKE-READY | AC89: =M89 -> PER/M | AE89: =O89 -> MAKE-READY | AG89: =M89 -> PER/M | AI89: =K89 -> MAKE-READY | AK89: =M89 -> PER/M | AM89: =K89 -> MAKE-READY | AO89: =M89 -> PER/M
A90: 2ND REWINDER
A91: DIE CUT
A92: PERF - Cross
A93: PERF - Pattern
A94: PERF - Vertical
A95: VERSION PLATE & PRESS STOP
A100: INK PRICES, PER SQUARE INCH | K100: MAKE-READY | M100: PER/M | O100: =K100 -> MAKE-READY | Q100: =M100 -> PER/M | S100: =K100 -> MAKE-READY | U100: =M100 -> PER/M | W100: =K100 -> MAKE-READY | Y100: =M100 -> PER/M | AA100: =K100 -> MAKE-READY | AC100: =M100 -> PER/M | AE100: =O100 -> MAKE-READY | AG100: =M100 -> PER/M | AI100: =K100 -> MAKE-READY | AK100: =M100 -> PER/M | AM100: =K100 -> MAKE-READY | AO100: =M100 -> PER/M
A101: 0/COLOR | C101: SHEETFED | M101: =(ROUND(0.462*B100/8.25*D100/10.875,4))*1.08 -> 0 | Q101: =M101 -> 0 | U101: =M101 -> 0 | AA101: =$K101*(1+$AI$2) -> 0 | AC101: =$M101 -> 0 | AE101: =$O101*(1+$AI$2) -> 0 | AG101: =$Q101 -> 0 | AI101: =IF(ISBLANK(W101),VLOOKUP(A101,A101:AG101,VLOOKUP($S$1,'Price Schedule (2)'!$BA$2:$BC$6,2,FALSE),FALSE),W101) -> 0 | AK101: =IF(ISBLANK(Y101),VLOOKUP(A101,A101:AG101,VLOOKUP($S$1,'Price Schedule (2)'!$BA$2:$BC$6,3,FALSE),FALSE),Y101) -> 0 | AM101: =IF(AND(K101=0,W101=0),0,IF(K101=0,"BM is $0",(AI101-K101)/K101)) -> 0 | AO101: =IF(AND(M101=0,Y101=0),0,IF(M101=0,"BM is $0",(AK101-M101)/M101)) -> 0 | AQ101: 8% ink increase applied 2/27/18
A102: 1/COLOR - K | C102: SHEETFED | M102: =0.003*1.15 -> 0.00345 | Q102: =M102 -> 0.00345 | U102: =M102 -> 0.00345 | AA102: =$K102*(1+$AI$2) -> 0 | AC102: =$M102 -> 0.00345 | AE102: =$O102*(1+$AI$2) -> 0 | AG102: =$Q102 -> 0.00345 | AI102: =IF(ISBLANK(W102),VLOOKUP(A102,A102:AG102,VLOOKUP($S$1,'Price Schedule (2)'!$BA$2:$BC$6,2,FALSE),FALSE),W102) -> 0 | AK102: =IF(ISBLANK(Y102),VLOOKUP(A102,A102:AG102,VLOOKUP($S$1,'Price Schedule (2)'!$BA$2:$BC$6,3,FALSE),FALSE),Y102) -> 0.00345 | AM102: =IF(AND(K102=0,W102=0),0,IF(K102=0,"BM is $0",(AI102-K102)/K102)) -> 0 | AO102: =IF(AND(M102=0,Y102=0),0,IF(M102=0,"BM is $0",(AK102-M102)/M102)) -> 0
A103: 1/COLOR - STD PMS | C103: SHEETFED | M103: =0.005676*1.15 -> 0.0065274 | Q103: =M103 -> 0.0065274 | U103: =M103 -> 0.0065274 | AA103: =$K103*(1+$AI$2) -> 0 | AC103: =$M103 -> 0.0065274 | AE103: =$O103*(1+$AI$2) -> 0 | AG103: =$Q103 -> 0.0065274 | AI103: =IF(ISBLANK(W103),VLOOKUP(A103,A103:AG103,VLOOKUP($S$1,'Price Schedule (2)'!$BA$2:$BC$6,2,FALSE),FALSE),W103) -> 0 | AK103: =IF(ISBLANK(Y103),VLOOKUP(A103,A103:AG103,VLOOKUP($S$1,'Price Schedule (2)'!$BA$2:$BC$6,3,FALSE),FALSE),Y103) -> 0.0065274 | AM103: =IF(AND(K103=0,W103=0),0,IF(K103=0,"BM is $0",(AI103-K103)/K103)) -> 0 | AO103: =IF(AND(M103=0,Y103=0),0,IF(M103=0,"BM is $0",(AK103-M103)/M103)) -> 0
A104: 4/COLOR PROCESS | C104: SHEETFED | M104: =0.01732*1.15 -> 0.019918 | Q104: =M104 -> 0.019918 | U104: =M104 -> 0.019918 | AA104: =$K104*(1+$AI$2) -> 0 | AC104: =$M104 -> 0.019918 | AE104: =$O104*(1+$AI$2) -> 0 | AG104: =$Q104 -> 0.019918 | AI104: =IF(ISBLANK(W104),VLOOKUP(A104,A104:AG104,VLOOKUP($S$1,'Price Schedule (2)'!$BA$2:$BC$6,2,FALSE),FALSE),W104) -> 0 | AK104: =IF(ISBLANK(Y104),VLOOKUP(A104,A104:AG104,VLOOKUP($S$1,'Price Schedule (2)'!$BA$2:$BC$6,3,FALSE),FALSE),Y104) -> 0.019918 | AM104: =IF(AND(K104=0,W104=0),0,IF(K104=0,"BM is $0",(AI104-K104)/K104)) -> 0 | AO104: =IF(AND(M104=0,Y104=0),0,IF(M104=0,"BM is $0",(AK104-M104)/M104)) -> 0
A105: MATTE/SATIN VARNISH | C105: SHEETFED | M105: =0.06167*1.115 -> 0.06876205 | Q105: =M105 -> 0.06876205 | U105: =M105 -> 0.06876205 | AA105: =$K105*(1+$AI$2) -> 0 | AC105: =$M105 -> 0.06876205 | AE105: =$O105*(1+$AI$2) -> 0 | AG105: =$Q105 -> 0.06876205 | AI105: =IF(ISBLANK(W105),VLOOKUP(A105,A105:AG105,VLOOKUP($S$1,'Price Schedule (2)'!$BA$2:$BC$6,2,FALSE),FALSE),W105) -> 0 | AK105: =IF(ISBLANK(Y105),VLOOKUP(A105,A105:AG105,VLOOKUP($S$1,'Price Schedule (2)'!$BA$2:$BC$6,3,FALSE),FALSE),Y105) -> 0.06876205 | AM105: =IF(AND(K105=0,W105=0),0,IF(K105=0,"BM is $0",(AI105-K105)/K105)) -> 0 | AO105: =IF(AND(M105=0,Y105=0),0,IF(M105=0,"BM is $0",(AK105-M105)/M105)) -> 0
A106: GLOSS VARNISH | C106: SHEETFED | M106: =0.03095*1.15 -> 0.0355925 | Q106: =M106 -> 0.0355925 | U106: =M106 -> 0.0355925 | AA106: =$K106*(1+$AI$2) -> 0 | AC106: =$M106 -> 0.0355925 | AE106: =$O106*(1+$AI$2) -> 0 | AG106: =$Q106 -> 0.0355925 | AI106: =IF(ISBLANK(W106),VLOOKUP(A106,A106:AG106,VLOOKUP($S$1,'Price Schedule (2)'!$BA$2:$BC$6,2,FALSE),FALSE),W106) -> 0 | AK106: =IF(ISBLANK(Y106),VLOOKUP(A106,A106:AG106,VLOOKUP($S$1,'Price Schedule (2)'!$BA$2:$BC$6,3,FALSE),FALSE),Y106) -> 0.0355925 | AM106: =IF(AND(K106=0,W106=0),0,IF(K106=0,"BM is $0",(AI106-K106)/K106)) -> 0 | AO106: =IF(AND(M106=0,Y106=0),0,IF(M106=0,"BM is $0",(AK106-M106)/M106)) -> 0
A107: 0/COLOR | C107: OFFSET | M107: 0 | Q107: =M107 -> 0 | U107: =M107 -> 0 | AA107: =$K107*(1+$AI$2) -> 0 | AC107: =$M107 -> 0 | AE107: =$O107*(1+$AI$2) -> 0 | AG107: =$Q107 -> 0 | AI107: =IF(ISBLANK(W107),VLOOKUP(A107,A107:AG107,VLOOKUP($S$1,'Price Schedule (2)'!$BA$2:$BC$6,2,FALSE),FALSE),W107) -> 0 | AK107: =IF(ISBLANK(Y107),VLOOKUP(A107,A107:AG107,VLOOKUP($S$1,'Price Schedule (2)'!$BA$2:$BC$6,3,FALSE),FALSE),Y107) -> 0 | AM107: =IF(AND(K107=0,W107=0),0,IF(K107=0,"BM is $0",(AI107-K107)/K107)) -> 0 | AO107: =IF(AND(M107=0,Y107=0),0,IF(M107=0,"BM is $0",(AK107-M107)/M107)) -> 0
A108: 1/COLOR - K | C108: OFFSET | M108: 0.0009396 | Q108: =M108 -> 0.0009396 | U108: =M108 -> 0.0009396 | AA108: =$K108*(1+$AI$2) -> 0 | AC108: =$M108 -> 0.0009396 | AE108: =$O108*(1+$AI$2) -> 0 | AG108: =$Q108 -> 0.0009396 | AI108: =IF(ISBLANK(W108),VLOOKUP(A108,A108:AG108,VLOOKUP($S$1,'Price Schedule (2)'!$BA$2:$BC$6,2,FALSE),FALSE),W108) -> 0 | AK108: =IF(ISBLANK(Y108),VLOOKUP(A108,A108:AG108,VLOOKUP($S$1,'Price Schedule (2)'!$BA$2:$BC$6,3,FALSE),FALSE),Y108) -> 0.0009396 | AM108: =IF(AND(K108=0,W108=0),0,IF(K108=0,"BM is $0",(AI108-K108)/K108)) -> 0 | AO108: =IF(AND(M108=0,Y108=0),0,IF(M108=0,"BM is $0",(AK108-M108)/M108)) -> 0
A109: 1/COLOR - STD PMS | C109: OFFSET | M109: 0.0017604 | Q109: =M109 -> 0.0017604 | U109: =M109 -> 0.0017604 | AA109: =$K109*(1+$AI$2) -> 0 | AC109: =$M109 -> 0.0017604 | AE109: =$O109*(1+$AI$2) -> 0 | AG109: =$Q109 -> 0.0017604 | AI109: =IF(ISBLANK(W109),VLOOKUP(A109,A109:AG109,VLOOKUP($S$1,'Price Schedule (2)'!$BA$2:$BC$6,2,FALSE),FALSE),W109) -> 0 | AK109: =IF(ISBLANK(Y109),VLOOKUP(A109,A109:AG109,VLOOKUP($S$1,'Price Schedule (2)'!$BA$2:$BC$6,3,FALSE),FALSE),Y109) -> 0.0017604 | AM109: =IF(AND(K109=0,W109=0),0,IF(K109=0,"BM is $0",(AI109-K109)/K109)) -> 0 | AO109: =IF(AND(M109=0,Y109=0),0,IF(M109=0,"BM is $0",(AK109-M109)/M109)) -> 0
A110: 4/COLOR PROCESS | C110: OFFSET | M110: 0.0054648 | Q110: =M110 -> 0.0054648 | U110: =M110 -> 0.0054648 | AA110: =$K110*(1+$AI$2) -> 0 | AC110: =$M110 -> 0.0054648 | AE110: =$O110*(1+$AI$2) -> 0 | AG110: =$Q110 -> 0.0054648 | AI110: =IF(ISBLANK(W110),VLOOKUP(A110,A110:AG110,VLOOKUP($S$1,'Price Schedule (2)'!$BA$2:$BC$6,2,FALSE),FALSE),W110) -> 0 | AK110: =IF(ISBLANK(Y110),VLOOKUP(A110,A110:AG110,VLOOKUP($S$1,'Price Schedule (2)'!$BA$2:$BC$6,3,FALSE),FALSE),Y110) -> 0.0054648 | AM110: =IF(AND(K110=0,W110=0),0,IF(K110=0,"BM is $0",(AI110-K110)/K110)) -> 0 | AO110: =IF(AND(M110=0,Y110=0),0,IF(M110=0,"BM is $0",(AK110-M110)/M110)) -> 0
A111: MATTE/SATIN VARNISH | C111: OFFSET | M111: 0.019602 | Q111: =M111 -> 0.019602 | U111: =M111 -> 0.019602 | AA111: =$K111*(1+$AI$2) -> 0 | AC111: =$M111 -> 0.019602 | AE111: =$O111*(1+$AI$2) -> 0 | AG111: =$Q111 -> 0.019602 | AI111: =IF(ISBLANK(W111),VLOOKUP(A111,A111:AG111,VLOOKUP($S$1,'Price Schedule (2)'!$BA$2:$BC$6,2,FALSE),FALSE),W111) -> 0 | AK111: =IF(ISBLANK(Y111),VLOOKUP(A111,A111:AG111,VLOOKUP($S$1,'Price Schedule (2)'!$BA$2:$BC$6,3,FALSE),FALSE),Y111) -> 0.019602 | AM111: =IF(AND(K111=0,W111=0),0,IF(K111=0,"BM is $0",(AI111-K111)/K111)) -> 0 | AO111: =IF(AND(M111=0,Y111=0),0,IF(M111=0,"BM is $0",(AK111-M111)/M111)) -> 0
A112: GLOSS VARNISH | C112: OFFSET | M112: 0.0097416 | Q112: =M112 -> 0.0097416 | U112: =M112 -> 0.0097416 | AA112: =$K112*(1+$AI$2) -> 0 | AC112: =$M112 -> 0.0097416 | AE112: =$O112*(1+$AI$2) -> 0 | AG112: =$Q112 -> 0.0097416 | AI112: =IF(ISBLANK(W112),VLOOKUP(A112,A112:AG112,VLOOKUP($S$1,'Price Schedule (2)'!$BA$2:$BC$6,2,FALSE),FALSE),W112) -> 0 | AK112: =IF(ISBLANK(Y112),VLOOKUP(A112,A112:AG112,VLOOKUP($S$1,'Price Schedule (2)'!$BA$2:$BC$6,3,FALSE),FALSE),Y112) -> 0.0097416 | AM112: =IF(AND(K112=0,W112=0),0,IF(K112=0,"BM is $0",(AI112-K112)/K112)) -> 0 | AO112: =IF(AND(M112=0,Y112=0),0,IF(M112=0,"BM is $0",(AK112-M112)/M112)) -> 0
A113: 0/COLOR | C113: SANDEN | M113: 0 | Q113: =M113 -> 0 | U113: =M113 -> 0 | AA113: =$K113*(1+$AI$2) -> 0 | AC113: =$M113 -> 0 | AE113: =$O113*(1+$AI$2) -> 0 | AG113: =$Q113 -> 0 | AI113: =IF(ISBLANK(W113),VLOOKUP(A113,A113:AG113,VLOOKUP($S$1,'Price Schedule (2)'!$BA$2:$BC$6,2,FALSE),FALSE),W113) -> 0 | AK113: =IF(ISBLANK(Y113),VLOOKUP(A113,A113:AG113,VLOOKUP($S$1,'Price Schedule (2)'!$BA$2:$BC$6,3,FALSE),FALSE),Y113) -> 0 | AM113: =IF(AND(K113=0,W113=0),0,IF(K113=0,"BM is $0",(AI113-K113)/K113)) -> 0 | AO113: =IF(AND(M113=0,Y113=0),0,IF(M113=0,"BM is $0",(AK113-M113)/M113)) -> 0
A114: 1/COLOR - K | C114: SANDEN | M114: 0.00459 | Q114: =M114 -> 0.00459 | U114: =M114 -> 0.00459 | AA114: =$K114*(1+$AI$2) -> 0 | AC114: =$M114 -> 0.00459 | AE114: =$O114*(1+$AI$2) -> 0 | AG114: =$Q114 -> 0.00459 | AI114: =IF(ISBLANK(W114),VLOOKUP(A114,A114:AG114,VLOOKUP($S$1,'Price Schedule (2)'!$BA$2:$BC$6,2,FALSE),FALSE),W114) -> 0 | AK114: =IF(ISBLANK(Y114),VLOOKUP(A114,A114:AG114,VLOOKUP($S$1,'Price Schedule (2)'!$BA$2:$BC$6,3,FALSE),FALSE),Y114) -> 0.00459 | AM114: =IF(AND(K114=0,W114=0),0,IF(K114=0,"BM is $0",(AI114-K114)/K114)) -> 0 | AO114: =IF(AND(M114=0,Y114=0),0,IF(M114=0,"BM is $0",(AK114-M114)/M114)) -> 0
A115: 1/COLOR - STD PMS | C115: SANDEN | M115: 0.0087588 | Q115: =M115 -> 0.0087588 | U115: =M115 -> 0.0087588 | AA115: =$K115*(1+$AI$2) -> 0 | AC115: =$M115 -> 0.0087588 | AE115: =$O115*(1+$AI$2) -> 0 | AG115: =$Q115 -> 0.0087588 | AI115: =IF(ISBLANK(W115),VLOOKUP(A115,A115:AG115,VLOOKUP($S$1,'Price Schedule (2)'!$BA$2:$BC$6,2,FALSE),FALSE),W115) -> 0 | AK115: =IF(ISBLANK(Y115),VLOOKUP(A115,A115:AG115,VLOOKUP($S$1,'Price Schedule (2)'!$BA$2:$BC$6,3,FALSE),FALSE),Y115) -> 0.0087588 | AM115: =IF(AND(K115=0,W115=0),0,IF(K115=0,"BM is $0",(AI115-K115)/K115)) -> 0 | AO115: =IF(AND(M115=0,Y115=0),0,IF(M115=0,"BM is $0",(AK115-M115)/M115)) -> 0
A116: 4/COLOR PROCESS | C116: SANDEN | M116: 0.0267516 | Q116: =M116 -> 0.0267516 | U116: =M116 -> 0.0267516 | AA116: =$K116*(1+$AI$2) -> 0 | AC116: =$M116 -> 0.0267516 | AE116: =$O116*(1+$AI$2) -> 0 | AG116: =$Q116 -> 0.0267516 | AI116: =IF(ISBLANK(W116),VLOOKUP(A116,A116:AG116,VLOOKUP($S$1,'Price Schedule (2)'!$BA$2:$BC$6,2,FALSE),FALSE),W116) -> 0 | AK116: =IF(ISBLANK(Y116),VLOOKUP(A116,A116:AG116,VLOOKUP($S$1,'Price Schedule (2)'!$BA$2:$BC$6,3,FALSE),FALSE),Y116) -> 0.0267516 | AM116: =IF(AND(K116=0,W116=0),0,IF(K116=0,"BM is $0",(AI116-K116)/K116)) -> 0 | AO116: =IF(AND(M116=0,Y116=0),0,IF(M116=0,"BM is $0",(AK116-M116)/M116)) -> 0
A117: MATTE/SATIN VARNISH | C117: SANDEN | M117: 0.0953856 | Q117: =M117 -> 0.0953856 | U117: =M117 -> 0.0953856 | AA117: =$K117*(1+$AI$2) -> 0 | AC117: =$M117 -> 0.0953856 | AE117: =$O117*(1+$AI$2) -> 0 | AG117: =$Q117 -> 0.0953856 | AI117: =IF(ISBLANK(W117),VLOOKUP(A117,A117:AG117,VLOOKUP($S$1,'Price Schedule (2)'!$BA$2:$BC$6,2,FALSE),FALSE),W117) -> 0 | AK117: =IF(ISBLANK(Y117),VLOOKUP(A117,A117:AG117,VLOOKUP($S$1,'Price Schedule (2)'!$BA$2:$BC$6,3,FALSE),FALSE),Y117) -> 0.0953856 | AM117: =IF(AND(K117=0,W117=0),0,IF(K117=0,"BM is $0",(AI117-K117)/K117)) -> 0 | AO117: =IF(AND(M117=0,Y117=0),0,IF(M117=0,"BM is $0",(AK117-M117)/M117)) -> 0
A118: GLOSS VARNISH | C118: SANDEN | M118: 0.0476928 | Q118: =M118 -> 0.0476928 | U118: =M118 -> 0.0476928 | AA118: =$K118*(1+$AI$2) -> 0 | AC118: =$M118 -> 0.0476928 | AE118: =$O118*(1+$AI$2) -> 0 | AG118: =$Q118 -> 0.0476928 | AI118: =IF(ISBLANK(W118),VLOOKUP(A118,A118:AG118,VLOOKUP($S$1,'Price Schedule (2)'!$BA$2:$BC$6,2,FALSE),FALSE),W118) -> 0 | AK118: =IF(ISBLANK(Y118),VLOOKUP(A118,A118:AG118,VLOOKUP($S$1,'Price Schedule (2)'!$BA$2:$BC$6,3,FALSE),FALSE),Y118) -> 0.0476928 | AM118: =IF(AND(K118=0,W118=0),0,IF(K118=0,"BM is $0",(AI118-K118)/K118)) -> 0 | AO118: =IF(AND(M118=0,Y118=0),0,IF(M118=0,"BM is $0",(AK118-M118)/M118)) -> 0
A120: OFFLINE BINDERY | K120: MAKE-READY | M120: PER/M | O120: =K120 -> MAKE-READY | Q120: =M120 -> PER/M | S120: =K120 -> MAKE-READY | U120: =M120 -> PER/M | W120: =K120 -> MAKE-READY | Y120: =M120 -> PER/M | AA120: =K120 -> MAKE-READY | AC120: =M120 -> PER/M | AE120: =O120 -> MAKE-READY | AG120: =M120 -> PER/M | AI120: =K120 -> MAKE-READY | AK120: =M120 -> PER/M | AM120: =K120 -> MAKE-READY | AO120: =M120 -> PER/M
A121: DIE CUT - COUNTOUR OR SHAPES | E121: (/M Sheets) | K121: 175 | M121: 38.9 | O121: 150 | Q121: 37 | S121: 75 | U121: 24.3 | AA121: =$K121*(1+$AI$2) -> 210 | AC121: =$M121*(1+$AK$2) -> 46.68 | AE121: =$O121*(1+$AI$2) -> 180 | AG121: =$Q121*(1+$AK$2) -> 44.4 | AI121: =IF(ISBLANK(W121),VLOOKUP(A121,A121:AG121,VLOOKUP($S$1,'Price Schedule (2)'!$BA$2:$BC$6,2,FALSE),FALSE),W121) -> 150 | AK121: =IF(ISBLANK(Y121),VLOOKUP(A121,A121:AG121,VLOOKUP($S$1,'Price Schedule (2)'!$BA$2:$BC$6,3,FALSE),FALSE),Y121) -> 37 | AM121: =IF(AND(K121=0,W121=0),0,IF(K121=0,"BM is $0",(AI121-K121)/K121)) -> -0.14285714 | AO121: =IF(AND(M121=0,Y121=0),0,IF(M121=0,"BM is $0",(AK121-M121)/M121)) -> -0.048843188
A122: DIE CUT - HINGE/SPINE SCORES | E122: (/M Sheets) | K122: 100 | M122: 36 | O122: 75 | Q122: 32.5 | S122: 35 | U122: 22.1 | AA122: =$K122*(1+$AI$2) -> 120 | AC122: =$M122*(1+$AK$2) -> 43.2 | AE122: =$O122*(1+$AI$2) -> 90 | AG122: =$Q122*(1+$AK$2) -> 39 | AI122: =IF(ISBLANK(W122),VLOOKUP(A122,A122:AG122,VLOOKUP($S$1,'Price Schedule (2)'!$BA$2:$BC$6,2,FALSE),FALSE),W122) -> 75 | AK122: =IF(ISBLANK(Y122),VLOOKUP(A122,A122:AG122,VLOOKUP($S$1,'Price Schedule (2)'!$BA$2:$BC$6,3,FALSE),FALSE),Y122) -> 32.5 | AM122: =IF(AND(K122=0,W122=0),0,IF(K122=0,"BM is $0",(AI122-K122)/K122)) -> -0.25 | AO122: =IF(AND(M122=0,Y122=0),0,IF(M122=0,"BM is $0",(AK122-M122)/M122)) -> -0.097222222
...
